Workbook
Name ARMCXDOC: 'MC BA'!$D$12
Name ARMCXMID: 'MC BA'!$D$15
Name ARMMA: 'MC BA'!$D$21
Name ARMMIC: 'MC BA'!$D$24
Name ARMMID: 'MC BA'!$D$27
Name ARMTB: 'MC BA'!$D$18

Sheet MC BA
B2: P E T R O L E O B R A S I L E I R O S. A. P E T R O B R A S
B3: M E M Ó R I A D E C Á L C U L O D E M E D I Ç Ã O
B4: Razão Social: | D4: PA ARQUIVOS LTDA | I4: CNPJ: | J4: 34.409.656/0001-84 | L4: Item 1 PPU | M4: IAPEFARQ: | N4: ='Mapa Geral'!I41 -> 0.33333333
B5: Contrato SAP: | D5: 4600687006 | I5: Área contrato: | J5: Lote 2 | M5: FDM: | N5: 1
B6: Objeto: | D6: SERVIÇO DE GUARDA E GERENCIAMENTO DE DOCUMENTOS E INFORMAÇÕES DO ACERVO DA PETROBRAS | I6: Instr. contratual: | J6: 5900.0133214.25.2 | L6: Item 2 PPU | M6: IAPEFARQ: | N6: ='Mapa Geral'!K41 -> 0.76
I7: Período: | J7: 26/06/2026 à 25/07/2026 | M7: FDM: | N7: 1
C10: Item | D10: Descrição da atividade | I10: Unidade | J10: QExec | K10: QFinal | L10: Valor unitário | M10: Valor total a pagar | N10: Observações
C11: 1 | D11: Guarda de Documentos e Informações
D12: ARM-CX-DOC | E12: Armazenamento de caixas para documentos
C13: 1.1 | D13: QUAm-1 | E13: QBm | F13: QDm | G13: QNm | H13: QUAm | I13: UA | J13: =SUMIF(ConsolidadoPA[Contrato],D12,ConsolidadoPA[UA]) -> 108333.57 | K13: =J13*$N$5 -> 108333.57 | L13: =IFERROR(VLOOKUP(ARMCXDOC,TabelaPA[[Linha de Serviço PPU]:[PREÇO UNITÁRIO ]],3,FALSE),"N/A") -> 0.9 | M13: =K13*L13 -> 97500.213
D14: =SUMIF(ConsolidadoPA[Contrato],ARMCXDOC,ConsolidadoPA[QUAm-1]) -> 84801 | E14: =SUMIF(ConsolidadoPA[Contrato],D12,ConsolidadoPA[QBm]) -> 0 | F14: =SUMIF(ConsolidadoPA[Contrato],D12,ConsolidadoPA[QDm]) -> 0 | G14: =SUMIF(ConsolidadoPA[Contrato],D12,ConsolidadoPA[QNm]) -> 17366 | H14: =(D14-E14-F14)+G14 -> 102167
D15: ARM-CX-MID | E15: Armazenamento de caixas para mídias
C16: 1.2 | D16: QUAm-1 | E16: QBm | F16: QDm | G16: QNm | H16: QUAm | I16: UA | J16: =SUMIF(ConsolidadoPA[Contrato],D15,ConsolidadoPA[UA]) -> 0 | K16: =J16*$N$5 -> 0 | L16: =IFERROR(VLOOKUP(ARMCXMID,TabelaPA[[Linha de Serviço PPU]:[PREÇO UNITÁRIO ]],3,FALSE),"N/A") -> 0.9 | M16: =K16*L16 -> 0
D17: =SUMIF(ConsolidadoPA[Contrato],D15,ConsolidadoPA[QUAm-1]) -> 0 | E17: =SUMIF(ConsolidadoPA[Contrato],D15,ConsolidadoPA[QBm]) -> 0 | F17: =SUMIF(ConsolidadoPA[Contrato],D15,ConsolidadoPA[QDm]) -> 0 | G17: =SUMIF(ConsolidadoPA[Contrato],D15,ConsolidadoPA[QNm]) -> 0 | H17: =(D17-E17-F17)+G17 -> 0
D18: ARM-TB | E18: Armazenamento de tubos
C19: 1.3 | D19: QUAm-1 | E19: QBm | F19: QDm | G19: QNm | H19: QUAm | I19: UA | J19: =SUMIF(ConsolidadoPA[Contrato],D18,ConsolidadoPA[UA]) -> 6.6206897 | K19: =J19*$N$5 -> 6.6206897 | L19: =IFERROR(VLOOKUP(ARMTB,TabelaPA[[Linha de Serviço PPU]:[PREÇO UNITÁRIO ]],3,FALSE),"N/A") -> 0.9 | M19: =K19*L19 -> 5.9586207
D20: =SUMIF(ConsolidadoPA[Contrato],D18,ConsolidadoPA[QUAm-1]) -> 0 | E20: =SUMIF(ConsolidadoPA[Contrato],D18,ConsolidadoPA[QBm]) -> 0 | F20: =SUMIF(ConsolidadoPA[Contrato],D18,ConsolidadoPA[QDm]) -> 0 | G20: =SUMIF(ConsolidadoPA[Contrato],D18,ConsolidadoPA[QNm]) -> 2 | H20: =(D20-E20-F20)+G20 -> 2
D21: ARM-MA | E21: Armazenamento de mapotecas e arquivos de aço
C22: 1.4 | D22: QUAm-1 | E22: QBm | F22: QDm | G22: QNm | H22: QUAm | I22: UA | J22: =SUMIF(ConsolidadoPA[Contrato],D21,ConsolidadoPA[UA]) -> 0 | K22: =J22*$N$5 -> 0 | L22: =IFERROR(VLOOKUP(ARMMA,TabelaPA[[Linha de Serviço PPU]:[PREÇO UNITÁRIO ]],3,FALSE),"N/A") -> 70 | M22: =K22*L22 -> 0
D23: =SUMIF(ConsolidadoPA[Contrato],D21,ConsolidadoPA[QUAm-1]) -> 0 | E23: =SUMIF(ConsolidadoPA[Contrato],D21,ConsolidadoPA[QBm]) -> 0 | F23: =SUMIF(ConsolidadoPA[Contrato],D21,ConsolidadoPA[QDm]) -> 0 | G23: =SUMIF(ConsolidadoPA[Contrato],D21,ConsolidadoPA[QNm]) -> 0 | H23: =(D23-E23-F23)+G23 -> 0
D24: ARM-MIC | E24: Armazenamento de microformas
C25: 1.5 | D25: QUAm-1 | E25: QBm | F25: QDm | G25: QNm | H25: QUAm | I25: UA | J25: =SUMIF(ConsolidadoPA[Contrato],D24,ConsolidadoPA[UA]) -> 0 | K25: =J25*$N$5 -> 0 | L25: =IFERROR(VLOOKUP(ARMMIC,TabelaPA[[Linha de Serviço PPU]:[PREÇO UNITÁRIO ]],3,FALSE),"N/A") -> 0.1 | M25: =K25*L25 -> 0
D26: =SUMIF(ConsolidadoPA[Contrato],D24,ConsolidadoPA[QUAm-1]) -> 0 | E26: =SUMIF(ConsolidadoPA[Contrato],D24,ConsolidadoPA[QBm]) -> 0 | F26: =SUMIF(ConsolidadoPA[Contrato],D24,ConsolidadoPA[QDm]) -> 0 | G26: =SUMIF(ConsolidadoPA[Contrato],D24,ConsolidadoPA[QNm]) -> 0 | H26: =(D26-E26-F26)+G26 -> 0
D27: ARM-MID | E27: Armazenamento de midias
C28: 1.6 | D28: QUAm-1 | E28: QBm | F28: QDm | G28: QNm | H28: QUAm | I28: UA | J28: =SUMIF(ConsolidadoPA[Contrato],D27,ConsolidadoPA[UA]) -> 0 | K28: =J28*$N$5 -> 0 | L28: =IFERROR(VLOOKUP(ARMMID,TabelaPA[[Linha de Serviço PPU]:[PREÇO UNITÁRIO ]],3,FALSE),"N/A") -> 0.1 | M28: =K28*L28 -> 0
D29: =SUMIF(ConsolidadoPA[Contrato],D27,ConsolidadoPA[QUAm-1]) -> 0 | E29: =SUMIF(ConsolidadoPA[Contrato],D27,ConsolidadoPA[QBm]) -> 0 | F29: =SUMIF(ConsolidadoPA[Contrato],D27,ConsolidadoPA[QDm]) -> 0 | G29: =SUMIF(ConsolidadoPA[Contrato],D27,ConsolidadoPA[QNm]) -> 0 | H29: =(D29-E29-F29)+G29 -> 0
C30: 1.7 | D30: FRE-NRM | E30: Frete normal | I30: Frete | J30: =SUMIF(Table_5[Tipo],"FRE-NRM",Table_5[Cálculo final]) -> 2 | K30: =J30*$N$5 -> 2 | L30: =IFERROR(VLOOKUP(D30,TabelaPA[[Linha de Serviço PPU]:[PREÇO UNITÁRIO ]],3,FALSE),"N/A") -> 50 | M30: =K30*L30 -> 100
C31: 1.8 | D31: FRE-EXP | E31: Frete expresso | I31: Frete | J31: =SUMIF(Table_5[Tipo],"FRE-EXP",Table_5[Cálculo final]) -> 0 | K31: =J31*$N$5 -> 0 | L31: =IFERROR(VLOOKUP(D31,TabelaPA[[Linha de Serviço PPU]:[PREÇO UNITÁRIO ]],3,FALSE),"N/A") -> 100 | M31: =K31*L31 -> 0
C32: 1.9 | D32: KM-AD | E32: Quilometragem adicional | I32: KM | J32: =SUMIF(Table_5[Tipo],"KM-AD",Table_5[KM excedente]) -> 3208 | K32: =J32*$N$5 -> 3208 | L32: =IFERROR(VLOOKUP(D32,TabelaPA[[Linha de Serviço PPU]:[PREÇO UNITÁRIO ]],3,FALSE),"N/A") -> 1 | M32: =K32*L32 -> 3208
C33: 1.10 | D33: PES-ITEM | E33: Pesquisa de itens avulsos | I33: Item Avulso | J33: ='Digitalização Click'!C36 -> 436 | K33: =J33*$N$5 -> 436 | L33: =IFERROR(VLOOKUP(D33,TabelaPA[[Linha de Serviço PPU]:[PREÇO UNITÁRIO ]],3,FALSE),"N/A") -> 3 | M33: =K33*L33 -> 1308
C34: 1.11 | D34: DES-EMB | E34: Destruição segura de documentos | I34: Item Avulso | J34: 0 | K34: =J34*$N$5 -> 0 | L34: =IFERROR(VLOOKUP(D34,TabelaPA[[Linha de Serviço PPU]:[PREÇO UNITÁRIO ]],3,FALSE),"N/A") -> 3 | M34: =K34*L35 -> 0
C35: 1.12 | D35: TRANSF | E35: Transferência inicial de acervo documental | I35: Transferência | J35: 0 | K35: =J35*$N$5 -> 0 | L35: =IFERROR(VLOOKUP(D35,TabelaPA[[Linha de Serviço PPU]:[PREÇO UNITÁRIO ]],3,FALSE),"N/A") -> 100000 | M35: 0
C36: 1.13 | D36: MIGR-UA | E36: Migração de acervo documental para digitalização | I36: UA | J36: 0 | K36: =J36*$N$5 -> 0 | L36: =IFERROR(VLOOKUP(D36,TabelaPA[[Linha de Serviço PPU]:[PREÇO UNITÁRIO ]],3,FALSE),"N/A") -> 7.5 | M36: =K36*L36 -> 0
C37: 2 | D37: Gerenciamento de Documentos e Informações
C38: 2.1 | D38: CAT-ITEM | E38: Catalogação de documentos digitalizados | I38: Documento | J38: 0 | K38: =J38*$N$7 -> 0 | L38: =IFERROR(VLOOKUP(D38,TabelaPA[[Linha de Serviço PPU]:[PREÇO UNITÁRIO ]],3,FALSE),"N/A") -> 0.2 | M38: =K38*L38 -> 0
C39: 2.2 | D39: ORG-DOC | E39: Organização de documentos para digitalização | I39: UA | J39: 0 | K39: =J39*$N$7 -> 0 | L39: =IFERROR(VLOOKUP(D39,TabelaPA[[Linha de Serviço PPU]:[PREÇO UNITÁRIO ]],3,FALSE),"N/A") -> 10 | M39: =K39*L39 -> 0
C40: 2.3 | D40: DIG-MI | E40: Digitalização de microfilmes | I40: UD | J40: 0 | K40: =J40*$N$7 -> 0 | L40: =IFERROR(VLOOKUP(D40,TabelaPA[[Linha de Serviço PPU]:[PREÇO UNITÁRIO ]],3,FALSE),"N/A") -> 0.05 | M40: =K40*L40 -> 0
C41: 2.4 | D41: DIG-MF | E41: Digitalização de microfichas | I41: UD | J41: ='Digitalização Click'!C30 -> 51 | K41: =J41*$N$7 -> 51 | L41: =IFERROR(VLOOKUP(D41,TabelaPA[[Linha de Serviço PPU]:[PREÇO UNITÁRIO ]],3,FALSE),"N/A") -> 0.05 | M41: =K41*L41 -> 2.55
C42: 2.5 | D42: DIG-DOC | E42: Digitalização de documentos | I42: UD | J42: ='Digitalização Click'!C32 -> 34544 | K42: =J42*$N$7 -> 34544 | L42: =IFERROR(VLOOKUP(D42,TabelaPA[[Linha de Serviço PPU]:[PREÇO UNITÁRIO ]],3,FALSE),"N/A") -> 0.11 | M42: =K42*L42 -> 3799.84
C43: 2.6 | D43: IND-DOC | E43: Indexação de documentos | I43: UD | J43: ='Digitalização Click'!C31 -> 436 | K43: =J43*$N$7 -> 436 | L43: =IFERROR(VLOOKUP(D43,TabelaPA[[Linha de Serviço PPU]:[PREÇO UNITÁRIO ]],3,FALSE),"N/A") -> 0.1 | M43: =K43*L43 -> 43.6
C44: 2.7 | D44: CONV-MID | E44: Conversão de mídias | I44: Mídia | J44: 0 | K44: =J44*$N$7 -> 0 | L44: =IFERROR(VLOOKUP(D44,TabelaPA[[Linha de Serviço PPU]:[PREÇO UNITÁRIO ]],3,FALSE),"N/A") -> 40 | M44: =K44*L44 -> 0
C45: 2.8 | D45: GRV-MID | E45: Gravação de mídias | I45: Mídia | J45: ='Digitalização Click'!C30 -> 51 | K45: =J45*$N$7 -> 51 | L45: =IFERROR(VLOOKUP(D45,TabelaPA[[Linha de Serviço PPU]:[PREÇO UNITÁRIO ]],3,FALSE),"N/A") -> 40 | M45: =K45*L45 -> 2040
C46: 2.9 | D46: COP-MID | E46: Cópia de mídias | I46: Mídia | J46: 0 | K46: =J46*$N$7 -> 0 | L46: =IFERROR(VLOOKUP(D46,TabelaPA[[Linha de Serviço PPU]:[PREÇO UNITÁRIO ]],3,FALSE),"N/A") -> 5 | M46: =K46*L46 -> 0
C47: TOTAL DO RM | M47: =SUM(M12:M46) -> 108008.16
C48: REPRESENTANTE DA PETROBRAS | J48: REPRESENTANTE DA CONTRATADA
J49: Rafael Mello Pimentel
C50: OBSERVAÇÕES GERAIS
D53: PEDIDO | E53: FRS | F53: RM | G53: NL | I53: VALOR | J53: COMENTÁRIOS DA FISCALIZAÇÃO

Sheet Consolidado
A1: Consolidado BA | J1: mês anterior | K1: Saída/mês | L1: Exp./Mês | M1: Novas/mês | N1: QUAm = QUAm-1 + QNm - QBm - QDm
C2: Formula | D2: Formula | E2: Formula | F2: Formula | G2: Formula | H2: Formula | J2: Editar | K2: Editar | L2: Editar | M2: Editar | N2: Formula | O2: Formula | P2: Formula | Q2: Formula
A3: MEDIDAS CONTRATO | B3: Padrão | C3: Ø | D3: A | E3: L | F3: P | G3: cm³ = V1 | H3: cm³ = V2 | I3: FC = V1/V2 | J3: QUAm-1 | K3: QBm | L3: QDm | M3: QNm | N3: QUAm | O3: UA | P3: $ Unitário | Q3: $ Total | R3: Tabela | S3: Contrato
A4: A 26,0 X L 39,5 X P 48,5 | B4: Caixa 20 kg - Tipo 1 | C4: =IF(ConsolidadoPA[[#This Row],[MEDIDAS CONTRATO]]="","", IFERROR( VLOOKUP(ConsolidadoPA[[#This Row],[MEDIDAS CONTRATO]],MedidasContrato[[MEDIDAS CONTRATO]:[Ø]],2,0),"N/A")) -> 0 | D4: =IF( ConsolidadoPA[[#This Row],[MEDIDAS CONTRATO]] = "", "", IFERROR( VLOOKUP(ConsolidadoPA[[#This Row],[MEDIDAS CONTRATO]],MedidasContrato[],3,0),"N/A")) -> 26 | E4: =IF( ConsolidadoPA[[#This Row],[MEDIDAS CONTRATO]] = "", "", IFERROR( VLOOKUP(ConsolidadoPA[[#This Row],[MEDIDAS CONTRATO]],MedidasContrato[],4,0),"N/A")) -> 39.5 | F4: =IF( ConsolidadoPA[[#This Row],[MEDIDAS CONTRATO]] = "", "", IFERROR( VLOOKUP(ConsolidadoPA[[#This Row],[MEDIDAS CONTRATO]],MedidasContrato[],5,0),"N/A")) -> 48.5 | G4: =IFERROR( ConsolidadoPA[[#This Row],[A]]*ConsolidadoPA[[#This Row],[L]]*ConsolidadoPA[[#This Row],[P]], "") -> 49809.5 | H4: 43993 | I4: =IFERROR( ConsolidadoPA[[#This Row],[cm³ = V1]]/ConsolidadoPA[[#This Row],[cm³ = V2]],"") -> 1.1322142 | J4: 4 | M4: 1 | N4: =IF( ConsolidadoPA[[#This Row],[QUAm-1]]="","",Consolidado!$M4+Consolidado!$J4-Consolidado!$L4-Consolidado!$K4) -> 5 | O4: =IF(ConsolidadoPA[[#This Row],[FC = V1/V2]]="","",ConsolidadoPA[[#This Row],[FC = V1/V2]]*ConsolidadoPA[[#This Row],[QUAm]]) -> 5.6610711 | P4: =IF( ConsolidadoPA[[#This Row],[Contrato]] = "", "", IFERROR( VLOOKUP(ConsolidadoPA[[#This Row],[Contrato]],TabelaPA[[Linha de Serviço PPU]:[PREÇO UNITÁRIO ]],3,0),"Nao Encontrado")) -> 0.9 | Q4: =IF(ConsolidadoPA[[#This Row],[$ Unitário]]="","",Consolidado!$P4*Consolidado!$O4) -> 5.094964 | R4: FC1 | S4: ARM-CX-DOC
A5: A 26,5 X L 38,5 X P 46,5 | B5: Caixa 20 kg - Tipo 1 | C5: =IF(ConsolidadoPA[[#This Row],[MEDIDAS CONTRATO]]="","", IFERROR( VLOOKUP(ConsolidadoPA[[#This Row],[MEDIDAS CONTRATO]],MedidasContrato[[MEDIDAS CONTRATO]:[Ø]],2,0),"N/A")) -> 0 | D5: =IF( ConsolidadoPA[[#This Row],[MEDIDAS CONTRATO]] = "", "", IFERROR( VLOOKUP(ConsolidadoPA[[#This Row],[MEDIDAS CONTRATO]],MedidasContrato[],3,0),"N/A")) -> 26.5 | E5: =IF( ConsolidadoPA[[#This Row],[MEDIDAS CONTRATO]] = "", "", IFERROR( VLOOKUP(ConsolidadoPA[[#This Row],[MEDIDAS CONTRATO]],MedidasContrato[],4,0),"N/A")) -> 38.5 | F5: =IF( ConsolidadoPA[[#This Row],[MEDIDAS CONTRATO]] = "", "", IFERROR( VLOOKUP(ConsolidadoPA[[#This Row],[MEDIDAS CONTRATO]],MedidasContrato[],5,0),"N/A")) -> 46.5 | G5: =IFERROR( ConsolidadoPA[[#This Row],[A]]*ConsolidadoPA[[#This Row],[L]]*ConsolidadoPA[[#This Row],[P]], "") -> 47441.625 | H5: 43993 | I5: =IFERROR( ConsolidadoPA[[#This Row],[cm³ = V1]]/ConsolidadoPA[[#This Row],[cm³ = V2]],"") -> 1.0783903 | J5: 8 | M5: 0 | N5: =IF( ConsolidadoPA[[#This Row],[QUAm-1]]="","",Consolidado!$M5+Consolidado!$J5-Consolidado!$L5-Consolidado!$K5) -> 8 | O5: =IF(ConsolidadoPA[[#This Row],[FC = V1/V2]]="","",ConsolidadoPA[[#This Row],[FC = V1/V2]]*ConsolidadoPA[[#This Row],[QUAm]]) -> 8.6271225 | P5: =IF( ConsolidadoPA[[#This Row],[Contrato]] = "", "", IFERROR( VLOOKUP(ConsolidadoPA[[#This Row],[Contrato]],TabelaPA[[Linha de Serviço PPU]:[PREÇO UNITÁRIO ]],3,0),"Nao Encontrado")) -> 0.9 | Q5: =IF(ConsolidadoPA[[#This Row],[$ Unitário]]="","",Consolidado!$P5*Consolidado!$O5) -> 7.7644102 | R5: FC1 | S5: ARM-CX-DOC
A6: A 26,5 X L 40,0 X P 49,0 | B6: Caixa 20 kg - Tipo 1 | C6: =IF(ConsolidadoPA[[#This Row],[MEDIDAS CONTRATO]]="","", IFERROR( VLOOKUP(ConsolidadoPA[[#This Row],[MEDIDAS CONTRATO]],MedidasContrato[[MEDIDAS CONTRATO]:[Ø]],2,0),"N/A")) -> 0 | D6: =IF( ConsolidadoPA[[#This Row],[MEDIDAS CONTRATO]] = "", "", IFERROR( VLOOKUP(ConsolidadoPA[[#This Row],[MEDIDAS CONTRATO]],MedidasContrato[],3,0),"N/A")) -> 26.5 | E6: =IF( ConsolidadoPA[[#This Row],[MEDIDAS CONTRATO]] = "", "", IFERROR( VLOOKUP(ConsolidadoPA[[#This Row],[MEDIDAS CONTRATO]],MedidasContrato[],4,0),"N/A")) -> 40 | F6: =IF( ConsolidadoPA[[#This Row],[MEDIDAS CONTRATO]] = "", "", IFERROR( VLOOKUP(ConsolidadoPA[[#This Row],[MEDIDAS CONTRATO]],MedidasContrato[],5,0),"N/A")) -> 49 | G6: =IFERROR( ConsolidadoPA[[#This Row],[A]]*ConsolidadoPA[[#This Row],[L]]*ConsolidadoPA[[#This Row],[P]], "") -> 51940 | H6: 43993 | I6: =IFERROR( ConsolidadoPA[[#This Row],[cm³ = V1]]/ConsolidadoPA[[#This Row],[cm³ = V2]],"") -> 1.1806424 | J6: 17 | M6: 3 | N6: =IF( ConsolidadoPA[[#This Row],[QUAm-1]]="","",Consolidado!$M6+Consolidado!$J6-Consolidado!$L6-Consolidado!$K6) -> 20 | O6: =IF(ConsolidadoPA[[#This Row],[FC = V1/V2]]="","",ConsolidadoPA[[#This Row],[FC = V1/V2]]*ConsolidadoPA[[#This Row],[QUAm]]) -> 23.612847 | P6: =IF( ConsolidadoPA[[#This Row],[Contrato]] = "", "", IFERROR( VLOOKUP(ConsolidadoPA[[#This Row],[Contrato]],TabelaPA[[Linha de Serviço PPU]:[PREÇO UNITÁRIO ]],3,0),"Nao Encontrado")) -> 0.9 | Q6: =IF(ConsolidadoPA[[#This Row],[$ Unitário]]="","",Consolidado!$P6*Consolidado!$O6) -> 21.251563 | R6: FC1 | S6: ARM-CX-DOC
A7: A 28,0 X L 37,5 X P 47,5 | B7: Caixa 20 kg - Tipo 1 | C7: =IF(ConsolidadoPA[[#This Row],[MEDIDAS CONTRATO]]="","", IFERROR( VLOOKUP(ConsolidadoPA[[#This Row],[MEDIDAS CONTRATO]],MedidasContrato[[MEDIDAS CONTRATO]:[Ø]],2,0),"N/A")) -> 0 | D7: =IF( ConsolidadoPA[[#This Row],[MEDIDAS CONTRATO]] = "", "", IFERROR( VLOOKUP(ConsolidadoPA[[#This Row],[MEDIDAS CONTRATO]],MedidasContrato[],3,0),"N/A")) -> 28 | E7: =IF( ConsolidadoPA[[#This Row],[MEDIDAS CONTRATO]] = "", "", IFERROR( VLOOKUP(ConsolidadoPA[[#This Row],[MEDIDAS CONTRATO]],MedidasContrato[],4,0),"N/A")) -> 37.5 | F7: =IF( ConsolidadoPA[[#This Row],[MEDIDAS CONTRATO]] = "", "", IFERROR( VLOOKUP(ConsolidadoPA[[#This Row],[MEDIDAS CONTRATO]],MedidasContrato[],5,0),"N/A")) -> 47.5 | G7: =IFERROR( ConsolidadoPA[[#This Row],[A]]*ConsolidadoPA[[#This Row],[L]]*ConsolidadoPA[[#This Row],[P]], "") -> 49875 | H7: 43993 | I7: =IFERROR( ConsolidadoPA[[#This Row],[cm³ = V1]]/ConsolidadoPA[[#This Row],[cm³ = V2]],"") -> 1.1337031 | J7: 8084 | M7: 3011 | N7: =IF( ConsolidadoPA[[#This Row],[QUAm-1]]="","",Consolidado!$M7+Consolidado!$J7-Consolidado!$L7-Consolidado!$K7) -> 11095 | O7: =IF(ConsolidadoPA[[#This Row],[FC = V1/V2]]="","",ConsolidadoPA[[#This Row],[FC = V1/V2]]*ConsolidadoPA[[#This Row],[QUAm]]) -> 12578.436 | P7: =IF( ConsolidadoPA[[#This Row],[Contrato]] = "", "", IFERROR( VLOOKUP(ConsolidadoPA[[#This Row],[Contrato]],TabelaPA[[Linha de Serviço PPU]:[PREÇO UNITÁRIO ]],3,0),"Nao Encontrado")) -> 0.9 | Q7: =IF(ConsolidadoPA[[#This Row],[$ Unitário]]="","",Consolidado!$P7*Consolidado!$O7) -> 11320.592 | R7: FC1 | S7: ARM-CX-DOC
A8: A 28,0 X L 39,0 X P 46,0 | B8: Caixa 20 kg - Tipo 1 | C8: =IF(ConsolidadoPA[[#This Row],[MEDIDAS CONTRATO]]="","", IFERROR( VLOOKUP(ConsolidadoPA[[#This Row],[MEDIDAS CONTRATO]],MedidasContrato[[MEDIDAS CONTRATO]:[Ø]],2,0),"N/A")) -> 0 | D8: =IF( ConsolidadoPA[[#This Row],[MEDIDAS CONTRATO]] = "", "", IFERROR( VLOOKUP(ConsolidadoPA[[#This Row],[MEDIDAS CONTRATO]],MedidasContrato[],3,0),"N/A")) -> 28 | E8: =IF( ConsolidadoPA[[#This Row],[MEDIDAS CONTRATO]] = "", "", IFERROR( VLOOKUP(ConsolidadoPA[[#This Row],[MEDIDAS CONTRATO]],MedidasContrato[],4,0),"N/A")) -> 39 | F8: =IF( ConsolidadoPA[[#This Row],[MEDIDAS CONTRATO]] = "", "", IFERROR( VLOOKUP(ConsolidadoPA[[#This Row],[MEDIDAS CONTRATO]],MedidasContrato[],5,0),"N/A")) -> 46 | G8: =IFERROR( ConsolidadoPA[[#This Row],[A]]*ConsolidadoPA[[#This Row],[L]]*ConsolidadoPA[[#This Row],[P]], "") -> 50232 | H8: 43993 | I8: =IFERROR( ConsolidadoPA[[#This Row],[cm³ = V1]]/ConsolidadoPA[[#This Row],[cm³ = V2]],"") -> 1.141818 | J8: 1904 | M8: 645 | N8: =IF( ConsolidadoPA[[#This Row],[QUAm-1]]="","",Consolidado!$M8+Consolidado!$J8-Consolidado!$L8-Consolidado!$K8) -> 2549 | O8: =IF(ConsolidadoPA[[#This Row],[FC = V1/V2]]="","",ConsolidadoPA[[#This Row],[FC = V1/V2]]*ConsolidadoPA[[#This Row],[QUAm]]) -> 2910.4941 | P8: =IF( ConsolidadoPA[[#This Row],[Contrato]] = "", "", IFERROR( VLOOKUP(ConsolidadoPA[[#This Row],[Contrato]],TabelaPA[[Linha de Serviço PPU]:[PREÇO UNITÁRIO ]],3,0),"Nao Encontrado")) -> 0.9 | Q8: =IF(ConsolidadoPA[[#This Row],[$ Unitário]]="","",Consolidado!$P8*Consolidado!$O8) -> 2619.4447 | R8: FC1 | S8: ARM-CX-DOC
A9: A 29,0 X L 37,0 X P 43,0 | B9: Caixa 20 kg - Tipo 1 | C9: =IF(ConsolidadoPA[[#This Row],[MEDIDAS CONTRATO]]="","", IFERROR( VLOOKUP(ConsolidadoPA[[#This Row],[MEDIDAS CONTRATO]],MedidasContrato[[MEDIDAS CONTRATO]:[Ø]],2,0),"N/A")) -> 0 | D9: =IF( ConsolidadoPA[[#This Row],[MEDIDAS CONTRATO]] = "", "", IFERROR( VLOOKUP(ConsolidadoPA[[#This Row],[MEDIDAS CONTRATO]],MedidasContrato[],3,0),"N/A")) -> 29 | E9: =IF( ConsolidadoPA[[#This Row],[MEDIDAS CONTRATO]] = "", "", IFERROR( VLOOKUP(ConsolidadoPA[[#This Row],[MEDIDAS CONTRATO]],MedidasContrato[],4,0),"N/A")) -> 37 | F9: =IF( ConsolidadoPA[[#This Row],[MEDIDAS CONTRATO]] = "", "", IFERROR( VLOOKUP(ConsolidadoPA[[#This Row],[MEDIDAS CONTRATO]],MedidasContrato[],5,0),"N/A")) -> 43 | G9: =IFERROR( ConsolidadoPA[[#This Row],[A]]*ConsolidadoPA[[#This Row],[L]]*ConsolidadoPA[[#This Row],[P]], "") -> 46139 | H9: 43993 | I9: =IFERROR( ConsolidadoPA[[#This Row],[cm³ = V1]]/ConsolidadoPA[[#This Row],[cm³ = V2]],"") -> 1.0487805 | J9: 74783 | M9: 13706 | N9: =IF( ConsolidadoPA[[#This Row],[QUAm-1]]="","",Consolidado!$M9+Consolidado!$J9-Consolidado!$L9-Consolidado!$K9) -> 88489 | O9: =IF(ConsolidadoPA[[#This Row],[FC = V1/V2]]="","",ConsolidadoPA[[#This Row],[FC = V1/V2]]*ConsolidadoPA[[#This Row],[QUAm]]) -> 92805.537 | P9: =IF( ConsolidadoPA[[#This Row],[Contrato]] = "", "", IFERROR( VLOOKUP(ConsolidadoPA[[#This Row],[Contrato]],TabelaPA[[Linha de Serviço PPU]:[PREÇO UNITÁRIO ]],3,0),"Nao Encontrado")) -> 0.9 | Q9: =IF(ConsolidadoPA[[#This Row],[$ Unitário]]="","",Consolidado!$P9*Consolidado!$O9) -> 83524.983 | R9: FC1 | S9: ARM-CX-DOC
A10: A 29,5 X L 39,0 X P 46,0 | B10: Caixa 20 kg - Tipo 1 | C10: =IF(ConsolidadoPA[[#This Row],[MEDIDAS CONTRATO]]="","", IFERROR( VLOOKUP(ConsolidadoPA[[#This Row],[MEDIDAS CONTRATO]],MedidasContrato[[MEDIDAS CONTRATO]:[Ø]],2,0),"N/A")) -> 0 | D10: =IF( ConsolidadoPA[[#This Row],[MEDIDAS CONTRATO]] = "", "", IFERROR( VLOOKUP(ConsolidadoPA[[#This Row],[MEDIDAS CONTRATO]],MedidasContrato[],3,0),"N/A")) -> 29.5 | E10: =IF( ConsolidadoPA[[#This Row],[MEDIDAS CONTRATO]] = "", "", IFERROR( VLOOKUP(ConsolidadoPA[[#This Row],[MEDIDAS CONTRATO]],MedidasContrato[],4,0),"N/A")) -> 39 | F10: =IF( ConsolidadoPA[[#This Row],[MEDIDAS CONTRATO]] = "", "", IFERROR( VLOOKUP(ConsolidadoPA[[#This Row],[MEDIDAS CONTRATO]],MedidasContrato[],5,0),"N/A")) -> 46 | G10: =IFERROR( ConsolidadoPA[[#This Row],[A]]*ConsolidadoPA[[#This Row],[L]]*ConsolidadoPA[[#This Row],[P]], "") -> 52923 | H10: 43993 | I10: =IFERROR( ConsolidadoPA[[#This Row],[cm³ = V1]]/ConsolidadoPA[[#This Row],[cm³ = V2]],"") -> 1.2029868 | J10: 1 | M10: 0 | N10: =IF( ConsolidadoPA[[#This Row],[QUAm-1]]="","",Consolidado!$M10+Consolidado!$J10-Consolidado!$L10-Consolidado!$K10) -> 1 | O10: =IF(ConsolidadoPA[[#This Row],[FC = V1/V2]]="","",ConsolidadoPA[[#This Row],[FC = V1/V2]]*ConsolidadoPA[[#This Row],[QUAm]]) -> 1.2029868 | P10: =IF( ConsolidadoPA[[#This Row],[Contrato]] = "", "", IFERROR( VLOOKUP(ConsolidadoPA[[#This Row],[Contrato]],TabelaPA[[Linha de Serviço PPU]:[PREÇO UNITÁRIO ]],3,0),"Nao Encontrado")) -> 0.9 | Q10: =IF(ConsolidadoPA[[#This Row],[$ Unitário]]="","",Consolidado!$P10*Consolidado!$O10) -> 1.0826882 | R10: FC1 | S10: ARM-CX-DOC
A11: A 12,0 X L 34,0 X P 37,0 | B11: Caixa para mídias - Tipo 1 | C11: =IF(ConsolidadoPA[[#This Row],[MEDIDAS CONTRATO]]="","", IFERROR( VLOOKUP(ConsolidadoPA[[#This Row],[MEDIDAS CONTRATO]],MedidasContrato[[MEDIDAS CONTRATO]:[Ø]],2,0),"N/A")) -> 0 | D11: =IF( ConsolidadoPA[[#This Row],[MEDIDAS CONTRATO]] = "", "", IFERROR( VLOOKUP(ConsolidadoPA[[#This Row],[MEDIDAS CONTRATO]],MedidasContrato[],3,0),"N/A")) -> 12 | E11: =IF( ConsolidadoPA[[#This Row],[MEDIDAS CONTRATO]] = "", "", IFERROR( VLOOKUP(ConsolidadoPA[[#This Row],[MEDIDAS CONTRATO]],MedidasContrato[],4,0),"N/A")) -> 34 | F11: =IF( ConsolidadoPA[[#This Row],[MEDIDAS CONTRATO]] = "", "", IFERROR( VLOOKUP(ConsolidadoPA[[#This Row],[MEDIDAS CONTRATO]],MedidasContrato[],5,0),"N/A")) -> 37 | G11: =IFERROR( ConsolidadoPA[[#This Row],[A]]*ConsolidadoPA[[#This Row],[L]]*ConsolidadoPA[[#This Row],[P]], "") -> 15096 | H11: 15096 | I11: =IFERROR( ConsolidadoPA[[#This Row],[cm³ = V1]]/ConsolidadoPA[[#This Row],[cm³ = V2]],"") -> 1 | J11: 0 | N11: =IF( ConsolidadoPA[[#This Row],[QUAm-1]]="","",Consolidado!$M11+Consolidado!$J11-Consolidado!$L11-Consolidado!$K11) -> 0 | O11: =IF(ConsolidadoPA[[#This Row],[FC = V1/V2]]="","",ConsolidadoPA[[#This Row],[FC = V1/V2]]*ConsolidadoPA[[#This Row],[QUAm]]) -> 0 | P11: =IF( ConsolidadoPA[[#This Row],[Contrato]] = "", "", IFERROR( VLOOKUP(ConsolidadoPA[[#This Row],[Contrato]],TabelaPA[[Linha de Serviço PPU]:[PREÇO UNITÁRIO ]],3,0),"Nao Encontrado")) -> 0.9 | Q11: =IF(ConsolidadoPA[[#This Row],[$ Unitário]]="","",Consolidado!$P11*Consolidado!$O11) -> 0 | R11: FC2 | S11: ARM-CX-MID
A12: A 11,5 X L 37,0 X P 33,0 | B12: Caixa para mídias - Tipo 1 | C12: =IF(ConsolidadoPA[[#This Row],[MEDIDAS CONTRATO]]="","", IFERROR( VLOOKUP(ConsolidadoPA[[#This Row],[MEDIDAS CONTRATO]],MedidasContrato[[MEDIDAS CONTRATO]:[Ø]],2,0),"N/A")) -> 0 | D12: =IF( ConsolidadoPA[[#This Row],[MEDIDAS CONTRATO]] = "", "", IFERROR( VLOOKUP(ConsolidadoPA[[#This Row],[MEDIDAS CONTRATO]],MedidasContrato[],3,0),"N/A")) -> 11.5 | E12: =IF( ConsolidadoPA[[#This Row],[MEDIDAS CONTRATO]] = "", "", IFERROR( VLOOKUP(ConsolidadoPA[[#This Row],[MEDIDAS CONTRATO]],MedidasContrato[],4,0),"N/A")) -> 37 | F12: =IF( ConsolidadoPA[[#This Row],[MEDIDAS CONTRATO]] = "", "", IFERROR( VLOOKUP(ConsolidadoPA[[#This Row],[MEDIDAS CONTRATO]],MedidasContrato[],5,0),"N/A")) -> 33 | G12: =IFERROR( ConsolidadoPA[[#This Row],[A]]*ConsolidadoPA[[#This Row],[L]]*ConsolidadoPA[[#This Row],[P]], "") -> 14041.5 | H12: 15096 | I12: =IFERROR( ConsolidadoPA[[#This Row],[cm³ = V1]]/ConsolidadoPA[[#This Row],[cm³ = V2]],"") -> 0.93014706 | J12: 0 | N12: =IF( ConsolidadoPA[[#This Row],[QUAm-1]]="","",Consolidado!$M12+Consolidado!$J12-Consolidado!$L12-Consolidado!$K12) -> 0 | O12: =IF(ConsolidadoPA[[#This Row],[FC = V1/V2]]="","",ConsolidadoPA[[#This Row],[FC = V1/V2]]*ConsolidadoPA[[#This Row],[QUAm]]) -> 0 | P12: =IF( ConsolidadoPA[[#This Row],[Contrato]] = "", "", IFERROR( VLOOKUP(ConsolidadoPA[[#This Row],[Contrato]],TabelaPA[[Linha de Serviço PPU]:[PREÇO UNITÁRIO ]],3,0),"Nao Encontrado")) -> 0.9 | Q12: =IF(ConsolidadoPA[[#This Row],[$ Unitário]]="","",Consolidado!$P12*Consolidado!$O12) -> 0 | R12: FC2 | S12: ARM-CX-MID
A13: L 10 x P 30 | B13: Tubo de engenharia | C13: =IF(ConsolidadoPA[[#This Row],[MEDIDAS CONTRATO]]="","", IFERROR( VLOOKUP(ConsolidadoPA[[#This Row],[MEDIDAS CONTRATO]],MedidasContrato[[MEDIDAS CONTRATO]:[Ø]],2,0),"N/A")) -> 0 | D13: =IF( ConsolidadoPA[[#This Row],[MEDIDAS CONTRATO]] = "", "", IFERROR( VLOOKUP(ConsolidadoPA[[#This Row],[MEDIDAS CONTRATO]],MedidasContrato[],3,0),"N/A")) -> 104 | E13: =IF( ConsolidadoPA[[#This Row],[MEDIDAS CONTRATO]] = "", "", IFERROR( VLOOKUP(ConsolidadoPA[[#This Row],[MEDIDAS CONTRATO]],MedidasContrato[],4,0),"N/A")) -> 10 | F13: =IF( ConsolidadoPA[[#This Row],[MEDIDAS CONTRATO]] = "", "", IFERROR( VLOOKUP(ConsolidadoPA[[#This Row],[MEDIDAS CONTRATO]],MedidasContrato[],5,0),"N/A")) -> 30 | G13: =IFERROR( ConsolidadoPA[[#This Row],[A]]*ConsolidadoPA[[#This Row],[L]]*ConsolidadoPA[[#This Row],[P]], "") -> 31200 | H13: 9425 | I13: =IFERROR( ConsolidadoPA[[#This Row],[cm³ = V1]]/ConsolidadoPA[[#This Row],[cm³ = V2]],"") -> 3.3103448 | J13: 0 | M13: 2 | N13: =IF( ConsolidadoPA[[#This Row],[QUAm-1]]="","",Consolidado!$M13+Consolidado!$J13-Consolidado!$L13-Consolidado!$K13) -> 2 | O13: =IF(ConsolidadoPA[[#This Row],[FC = V1/V2]]="","",ConsolidadoPA[[#This Row],[FC = V1/V2]]*ConsolidadoPA[[#This Row],[QUAm]]) -> 6.6206897 | P13: =IF( ConsolidadoPA[[#This Row],[Contrato]] = "", "", IFERROR( VLOOKUP(ConsolidadoPA[[#This Row],[Contrato]],TabelaPA[[Linha de Serviço PPU]:[PREÇO UNITÁRIO ]],3,0),"Nao Encontrado")) -> 0.9 | Q13: =IF(ConsolidadoPA[[#This Row],[$ Unitário]]="","",Consolidado!$P13*Consolidado!$O13) -> 5.9586207 | R13: FC3 | S13: ARM-TB
A14: L 0,11 X C 1,20 | B14: Tubo de engenharia | C14: =IF(ConsolidadoPA[[#This Row],[MEDIDAS CONTRATO]]="","", IFERROR( VLOOKUP(ConsolidadoPA[[#This Row],[MEDIDAS CONTRATO]],MedidasContrato[[MEDIDAS CONTRATO]:[Ø]],2,0),"N/A")) -> 0 | D14: =IF( ConsolidadoPA[[#This Row],[MEDIDAS CONTRATO]] = "", "", IFERROR( VLOOKUP(ConsolidadoPA[[#This Row],[MEDIDAS CONTRATO]],MedidasContrato[],3,0),"N/A")) -> 0 | E14: =IF( ConsolidadoPA[[#This Row],[MEDIDAS CONTRATO]] = "", "", IFERROR( VLOOKUP(ConsolidadoPA[[#This Row],[MEDIDAS CONTRATO]],MedidasContrato[],4,0),"N/A")) -> 0.11 | F14: =IF( ConsolidadoPA[[#This Row],[MEDIDAS CONTRATO]] = "", "", IFERROR( VLOOKUP(ConsolidadoPA[[#This Row],[MEDIDAS CONTRATO]],MedidasContrato[],5,0),"N/A")) -> 1.2 | G14: =IFERROR( ConsolidadoPA[[#This Row],[A]]*ConsolidadoPA[[#This Row],[L]]*ConsolidadoPA[[#This Row],[P]], "") -> 0 | H14: 9425 | I14: =IFERROR( ConsolidadoPA[[#This Row],[cm³ = V1]]/ConsolidadoPA[[#This Row],[cm³ = V2]],"") -> 0 | J14: 0 | N14: =IF( ConsolidadoPA[[#This Row],[QUAm-1]]="","",Consolidado!$M14+Consolidado!$J14-Consolidado!$L14-Consolidado!$K14) -> 0 | O14: =IF(ConsolidadoPA[[#This Row],[FC = V1/V2]]="","",ConsolidadoPA[[#This Row],[FC = V1/V2]]*ConsolidadoPA[[#This Row],[QUAm]]) -> 0 | P14: =IF( ConsolidadoPA[[#This Row],[Contrato]] = "", "", IFERROR( VLOOKUP(ConsolidadoPA[[#This Row],[Contrato]],TabelaPA[[Linha de Serviço PPU]:[PREÇO UNITÁRIO ]],3,0),"Nao Encontrado")) -> 0.9 | Q14: =IF(ConsolidadoPA[[#This Row],[$ Unitário]]="","",Consolidado!$P14*Consolidado!$O14) -> 0 | R14: FC3 | S14: ARM-TB
A15: L 0,11 X C 1,23 | B15: Tubo de engenharia | C15: =IF(ConsolidadoPA[[#This Row],[MEDIDAS CONTRATO]]="","", IFERROR( VLOOKUP(ConsolidadoPA[[#This Row],[MEDIDAS CONTRATO]],MedidasContrato[[MEDIDAS CONTRATO]:[Ø]],2,0),"N/A")) -> 0 | D15: =IF( ConsolidadoPA[[#This Row],[MEDIDAS CONTRATO]] = "", "", IFERROR( VLOOKUP(ConsolidadoPA[[#This Row],[MEDIDAS CONTRATO]],MedidasContrato[],3,0),"N/A")) -> 0 | E15: =IF( ConsolidadoPA[[#This Row],[MEDIDAS CONTRATO]] = "", "", IFERROR( VLOOKUP(ConsolidadoPA[[#This Row],[MEDIDAS CONTRATO]],MedidasContrato[],4,0),"N/A")) -> 0.11 | F15: =IF( ConsolidadoPA[[#This Row],[MEDIDAS CONTRATO]] = "", "", IFERROR( VLOOKUP(ConsolidadoPA[[#This Row],[MEDIDAS CONTRATO]],MedidasContrato[],5,0),"N/A")) -> 1.23 | G15: =IFERROR( ConsolidadoPA[[#This Row],[A]]*ConsolidadoPA[[#This Row],[L]]*ConsolidadoPA[[#This Row],[P]], "") -> 0 | H15: 9425 | I15: =IFERROR( ConsolidadoPA[[#This Row],[cm³ = V1]]/ConsolidadoPA[[#This Row],[cm³ = V2]],"") -> 0 | J15: 0 | N15: =IF( ConsolidadoPA[[#This Row],[QUAm-1]]="","",Consolidado!$M15+Consolidado!$J15-Consolidado!$L15-Consolidado!$K15) -> 0 | O15: =IF(ConsolidadoPA[[#This Row],[FC = V1/V2]]="","",ConsolidadoPA[[#This Row],[FC = V1/V2]]*ConsolidadoPA[[#This Row],[QUAm]]) -> 0 | P15: =IF( ConsolidadoPA[[#This Row],[Contrato]] = "", "", IFERROR( VLOOKUP(ConsolidadoPA[[#This Row],[Contrato]],TabelaPA[[Linha de Serviço PPU]:[PREÇO UNITÁRIO ]],3,0),"Nao Encontrado")) -> 0.9 | Q15: =IF(ConsolidadoPA[[#This Row],[$ Unitário]]="","",Consolidado!$P15*Consolidado!$O15) -> 0 | R15: FC3 | S15: ARM-TB
A16: L 0,11 X C 1,30 | B16: Tubo de engenharia | C16: =IF(ConsolidadoPA[[#This Row],[MEDIDAS CONTRATO]]="","", IFERROR( VLOOKUP(ConsolidadoPA[[#This Row],[MEDIDAS CONTRATO]],MedidasContrato[[MEDIDAS CONTRATO]:[Ø]],2,0),"N/A")) -> 0 | D16: =IF( ConsolidadoPA[[#This Row],[MEDIDAS CONTRATO]] = "", "", IFERROR( VLOOKUP(ConsolidadoPA[[#This Row],[MEDIDAS CONTRATO]],MedidasContrato[],3,0),"N/A")) -> 0 | E16: =IF( ConsolidadoPA[[#This Row],[MEDIDAS CONTRATO]] = "", "", IFERROR( VLOOKUP(ConsolidadoPA[[#This Row],[MEDIDAS CONTRATO]],MedidasContrato[],4,0),"N/A")) -> 0.11 | F16: =IF( ConsolidadoPA[[#This Row],[MEDIDAS CONTRATO]] = "", "", IFERROR( VLOOKUP(ConsolidadoPA[[#This Row],[MEDIDAS CONTRATO]],MedidasContrato[],5,0),"N/A")) -> 1.3 | G16: =IFERROR( ConsolidadoPA[[#This Row],[A]]*ConsolidadoPA[[#This Row],[L]]*ConsolidadoPA[[#This Row],[P]], "") -> 0 | H16: 9425 | I16: =IFERROR( ConsolidadoPA[[#This Row],[cm³ = V1]]/ConsolidadoPA[[#This Row],[cm³ = V2]],"") -> 0 | J16: 0 | N16: =IF( ConsolidadoPA[[#This Row],[QUAm-1]]="","",Consolidado!$M16+Consolidado!$J16-Consolidado!$L16-Consolidado!$K16) -> 0 | O16: =IF(ConsolidadoPA[[#This Row],[FC = V1/V2]]="","",ConsolidadoPA[[#This Row],[FC = V1/V2]]*ConsolidadoPA[[#This Row],[QUAm]]) -> 0 | P16: =IF( ConsolidadoPA[[#This Row],[Contrato]] = "", "", IFERROR( VLOOKUP(ConsolidadoPA[[#This Row],[Contrato]],TabelaPA[[Linha de Serviço PPU]:[PREÇO UNITÁRIO ]],3,0),"Nao Encontrado")) -> 0.9 | Q16: =IF(ConsolidadoPA[[#This Row],[$ Unitário]]="","",Consolidado!$P16*Consolidado!$O16) -> 0 | R16: FC3 | S16: ARM-TB
A17: L 0,11 X C 1,26 | B17: Tubo de engenharia | C17: =IF(ConsolidadoPA[[#This Row],[MEDIDAS CONTRATO]]="","", IFERROR( VLOOKUP(ConsolidadoPA[[#This Row],[MEDIDAS CONTRATO]],MedidasContrato[[MEDIDAS CONTRATO]:[Ø]],2,0),"N/A")) -> 0 | D17: =IF( ConsolidadoPA[[#This Row],[MEDIDAS CONTRATO]] = "", "", IFERROR( VLOOKUP(ConsolidadoPA[[#This Row],[MEDIDAS CONTRATO]],MedidasContrato[],3,0),"N/A")) -> 0 | E17: =IF( ConsolidadoPA[[#This Row],[MEDIDAS CONTRATO]] = "", "", IFERROR( VLOOKUP(ConsolidadoPA[[#This Row],[MEDIDAS CONTRATO]],MedidasContrato[],4,0),"N/A")) -> 0.11 | F17: =IF( ConsolidadoPA[[#This Row],[MEDIDAS CONTRATO]] = "", "", IFERROR( VLOOKUP(ConsolidadoPA[[#This Row],[MEDIDAS CONTRATO]],MedidasContrato[],5,0),"N/A")) -> 1.26 | G17: =IFERROR( ConsolidadoPA[[#This Row],[A]]*ConsolidadoPA[[#This Row],[L]]*ConsolidadoPA[[#This Row],[P]], "") -> 0 | H17: 9425 | I17: =IFERROR( ConsolidadoPA[[#This Row],[cm³ = V1]]/ConsolidadoPA[[#This Row],[cm³ = V2]],"") -> 0 | J17: 0 | N17: =IF( ConsolidadoPA[[#This Row],[QUAm-1]]="","",Consolidado!$M17+Consolidado!$J17-Consolidado!$L17-Consolidado!$K17) -> 0 | O17: =IF(ConsolidadoPA[[#This Row],[FC = V1/V2]]="","",ConsolidadoPA[[#This Row],[FC = V1/V2]]*ConsolidadoPA[[#This Row],[QUAm]]) -> 0 | P17: =IF( ConsolidadoPA[[#This Row],[Contrato]] = "", "", IFERROR( VLOOKUP(ConsolidadoPA[[#This Row],[Contrato]],TabelaPA[[Linha de Serviço PPU]:[PREÇO UNITÁRIO ]],3,0),"Nao Encontrado")) -> 0.9 | Q17: =IF(ConsolidadoPA[[#This Row],[$ Unitário]]="","",Consolidado!$P17*Consolidado!$O17) -> 0 | R17: FC3 | S17: ARM-TB
C18: =IF(ConsolidadoPA[[#This Row],[MEDIDAS CONTRATO]]="","", IFERROR( VLOOKUP(ConsolidadoPA[[#This Row],[MEDIDAS CONTRATO]],MedidasContrato[[MEDIDAS CONTRATO]:[Ø]],2,0),"N/A")) | D18: =IF( ConsolidadoPA[[#This Row],[MEDIDAS CONTRATO]] = "", "", IFERROR( VLOOKUP(ConsolidadoPA[[#This Row],[MEDIDAS CONTRATO]],MedidasContrato[],3,0),"N/A")) | E18: =IF( ConsolidadoPA[[#This Row],[MEDIDAS CONTRATO]] = "", "", IFERROR( VLOOKUP(ConsolidadoPA[[#This Row],[MEDIDAS CONTRATO]],MedidasContrato[],4,0),"N/A")) | F18: =IF( ConsolidadoPA[[#This Row],[MEDIDAS CONTRATO]] = "", "", IFERROR( VLOOKUP(ConsolidadoPA[[#This Row],[MEDIDAS CONTRATO]],MedidasContrato[],5,0),"N/A")) | G18: =IFERROR( ConsolidadoPA[[#This Row],[A]]*ConsolidadoPA[[#This Row],[L]]*ConsolidadoPA[[#This Row],[P]], "") | I18: =IFERROR( ConsolidadoPA[[#This Row],[cm³ = V1]]/ConsolidadoPA[[#This Row],[cm³ = V2]],"") | N18: =IF( ConsolidadoPA[[#This Row],[QUAm-1]]="","",Consolidado!$M18+Consolidado!$J18-Consolidado!$L18-Consolidado!$K18) | O18: =IF(ConsolidadoPA[[#This Row],[FC = V1/V2]]="","",ConsolidadoPA[[#This Row],[FC = V1/V2]]*ConsolidadoPA[[#This Row],[QUAm]]) | P18: =IF( ConsolidadoPA[[#This Row],[Contrato]] = "", "", IFERROR( VLOOKUP(ConsolidadoPA[[#This Row],[Contrato]],TabelaPA[[Linha de Serviço PPU]:[PREÇO UNITÁRIO ]],3,0),"Nao Encontrado")) | Q18: =IF(ConsolidadoPA[[#This Row],[$ Unitário]]="","",Consolidado!$P18*Consolidado!$O18)
C19: =IF(ConsolidadoPA[[#This Row],[MEDIDAS CONTRATO]]="","", IFERROR( VLOOKUP(ConsolidadoPA[[#This Row],[MEDIDAS CONTRATO]],MedidasContrato[[MEDIDAS CONTRATO]:[Ø]],2,0),"N/A")) | D19: =IF( ConsolidadoPA[[#This Row],[MEDIDAS CONTRATO]] = "", "", IFERROR( VLOOKUP(ConsolidadoPA[[#This Row],[MEDIDAS CONTRATO]],MedidasContrato[],3,0),"N/A")) | E19: =IF( ConsolidadoPA[[#This Row],[MEDIDAS CONTRATO]] = "", "", IFERROR( VLOOKUP(ConsolidadoPA[[#This Row],[MEDIDAS CONTRATO]],MedidasContrato[],4,0),"N/A")) | F19: =IF( ConsolidadoPA[[#This Row],[MEDIDAS CONTRATO]] = "", "", IFERROR( VLOOKUP(ConsolidadoPA[[#This Row],[MEDIDAS CONTRATO]],MedidasContrato[],5,0),"N/A")) | G19: =IFERROR( ConsolidadoPA[[#This Row],[A]]*ConsolidadoPA[[#This Row],[L]]*ConsolidadoPA[[#This Row],[P]], "") | I19: =IFERROR( ConsolidadoPA[[#This Row],[cm³ = V1]]/ConsolidadoPA[[#This Row],[cm³ = V2]],"") | N19: =IF( ConsolidadoPA[[#This Row],[QUAm-1]]="","",Consolidado!$M19+Consolidado!$J19-Consolidado!$L19-Consolidado!$K19) | O19: =IF(ConsolidadoPA[[#This Row],[FC = V1/V2]]="","",ConsolidadoPA[[#This Row],[FC = V1/V2]]*ConsolidadoPA[[#This Row],[QUAm]]) | P19: =IF( ConsolidadoPA[[#This Row],[Contrato]] = "", "", IFERROR( VLOOKUP(ConsolidadoPA[[#This Row],[Contrato]],TabelaPA[[Linha de Serviço PPU]:[PREÇO UNITÁRIO ]],3,0),"Nao Encontrado")) | Q19: =IF(ConsolidadoPA[[#This Row],[$ Unitário]]="","",Consolidado!$P19*Consolidado!$O19)
C20: =IF(ConsolidadoPA[[#This Row],[MEDIDAS CONTRATO]]="","", IFERROR( VLOOKUP(ConsolidadoPA[[#This Row],[MEDIDAS CONTRATO]],MedidasContrato[[MEDIDAS CONTRATO]:[Ø]],2,0),"N/A")) | D20: =IF( ConsolidadoPA[[#This Row],[MEDIDAS CONTRATO]] = "", "", IFERROR( VLOOKUP(ConsolidadoPA[[#This Row],[MEDIDAS CONTRATO]],MedidasContrato[],3,0),"N/A")) | E20: =IF( ConsolidadoPA[[#This Row],[MEDIDAS CONTRATO]] = "", "", IFERROR( VLOOKUP(ConsolidadoPA[[#This Row],[MEDIDAS CONTRATO]],MedidasContrato[],4,0),"N/A")) | F20: =IF( ConsolidadoPA[[#This Row],[MEDIDAS CONTRATO]] = "", "", IFERROR( VLOOKUP(ConsolidadoPA[[#This Row],[MEDIDAS CONTRATO]],MedidasContrato[],5,0),"N/A")) | G20: =IFERROR( ConsolidadoPA[[#This Row],[A]]*ConsolidadoPA[[#This Row],[L]]*ConsolidadoPA[[#This Row],[P]], "") | I20: =IFERROR( ConsolidadoPA[[#This Row],[cm³ = V1]]/ConsolidadoPA[[#This Row],[cm³ = V2]],"") | N20: =IF( ConsolidadoPA[[#This Row],[QUAm-1]]="","",Consolidado!$M20+Consolidado!$J20-Consolidado!$L20-Consolidado!$K20) | O20: =IF(ConsolidadoPA[[#This Row],[FC = V1/V2]]="","",ConsolidadoPA[[#This Row],[FC = V1/V2]]*ConsolidadoPA[[#This Row],[QUAm]]) | P20: =IF( ConsolidadoPA[[#This Row],[Contrato]] = "", "", IFERROR( VLOOKUP(ConsolidadoPA[[#This Row],[Contrato]],TabelaPA[[Linha de Serviço PPU]:[PREÇO UNITÁRIO ]],3,0),"Nao Encontrado")) | Q20: =IF(ConsolidadoPA[[#This Row],[$ Unitário]]="","",Consolidado!$P20*Consolidado!$O20)
C21: =IF(ConsolidadoPA[[#This Row],[MEDIDAS CONTRATO]]="","", IFERROR( VLOOKUP(ConsolidadoPA[[#This Row],[MEDIDAS CONTRATO]],MedidasContrato[[MEDIDAS CONTRATO]:[Ø]],2,0),"N/A")) | D21: =IF( ConsolidadoPA[[#This Row],[MEDIDAS CONTRATO]] = "", "", IFERROR( VLOOKUP(ConsolidadoPA[[#This Row],[MEDIDAS CONTRATO]],MedidasContrato[],3,0),"N/A")) | E21: =IF( ConsolidadoPA[[#This Row],[MEDIDAS CONTRATO]] = "", "", IFERROR( VLOOKUP(ConsolidadoPA[[#This Row],[MEDIDAS CONTRATO]],MedidasContrato[],4,0),"N/A")) | F21: =IF( ConsolidadoPA[[#This Row],[MEDIDAS CONTRATO]] = "", "", IFERROR( VLOOKUP(ConsolidadoPA[[#This Row],[MEDIDAS CONTRATO]],MedidasContrato[],5,0),"N/A")) | G21: =IFERROR( ConsolidadoPA[[#This Row],[A]]*ConsolidadoPA[[#This Row],[L]]*ConsolidadoPA[[#This Row],[P]], "") | I21: =IFERROR( ConsolidadoPA[[#This Row],[cm³ = V1]]/ConsolidadoPA[[#This Row],[cm³ = V2]],"") | N21: =IF( ConsolidadoPA[[#This Row],[QUAm-1]]="","",Consolidado!$M21+Consolidado!$J21-Consolidado!$L21-Consolidado!$K21) | O21: =IF(ConsolidadoPA[[#This Row],[FC = V1/V2]]="","",ConsolidadoPA[[#This Row],[FC = V1/V2]]*ConsolidadoPA[[#This Row],[QUAm]]) | P21: =IF( ConsolidadoPA[[#This Row],[Contrato]] = "", "", IFERROR( VLOOKUP(ConsolidadoPA[[#This Row],[Contrato]],TabelaPA[[Linha de Serviço PPU]:[PREÇO UNITÁRIO ]],3,0),"Nao Encontrado")) | Q21: =IF(ConsolidadoPA[[#This Row],[$ Unitário]]="","",Consolidado!$P21*Consolidado!$O21)
C22: =IF(ConsolidadoPA[[#This Row],[MEDIDAS CONTRATO]]="","", IFERROR( VLOOKUP(ConsolidadoPA[[#This Row],[MEDIDAS CONTRATO]],MedidasContrato[[MEDIDAS CONTRATO]:[Ø]],2,0),"N/A")) | D22: =IF( ConsolidadoPA[[#This Row],[MEDIDAS CONTRATO]] = "", "", IFERROR( VLOOKUP(ConsolidadoPA[[#This Row],[MEDIDAS CONTRATO]],MedidasContrato[],3,0),"N/A")) | E22: =IF( ConsolidadoPA[[#This Row],[MEDIDAS CONTRATO]] = "", "", IFERROR( VLOOKUP(ConsolidadoPA[[#This Row],[MEDIDAS CONTRATO]],MedidasContrato[],4,0),"N/A")) | F22: =IF( ConsolidadoPA[[#This Row],[MEDIDAS CONTRATO]] = "", "", IFERROR( VLOOKUP(ConsolidadoPA[[#This Row],[MEDIDAS CONTRATO]],MedidasContrato[],5,0),"N/A")) | G22: =IFERROR( ConsolidadoPA[[#This Row],[A]]*ConsolidadoPA[[#This Row],[L]]*ConsolidadoPA[[#This Row],[P]], "") | I22: =IFERROR( ConsolidadoPA[[#This Row],[cm³ = V1]]/ConsolidadoPA[[#This Row],[cm³ = V2]],"") | N22: =IF( ConsolidadoPA[[#This Row],[QUAm-1]]="","",Consolidado!$M22+Consolidado!$J22-Consolidado!$L22-Consolidado!$K22) | O22: =IF(ConsolidadoPA[[#This Row],[FC = V1/V2]]="","",ConsolidadoPA[[#This Row],[FC = V1/V2]]*ConsolidadoPA[[#This Row],[QUAm]]) | P22: =IF( ConsolidadoPA[[#This Row],[Contrato]] = "", "", IFERROR( VLOOKUP(ConsolidadoPA[[#This Row],[Contrato]],TabelaPA[[Linha de Serviço PPU]:[PREÇO UNITÁRIO ]],3,0),"Nao Encontrado")) | Q22: =IF(ConsolidadoPA[[#This Row],[$ Unitário]]="","",Consolidado!$P22*Consolidado!$O22)
C23: =IF(ConsolidadoPA[[#This Row],[MEDIDAS CONTRATO]]="","", IFERROR( VLOOKUP(ConsolidadoPA[[#This Row],[MEDIDAS CONTRATO]],MedidasContrato[[MEDIDAS CONTRATO]:[Ø]],2,0),"N/A")) | D23: =IF( ConsolidadoPA[[#This Row],[MEDIDAS CONTRATO]] = "", "", IFERROR( VLOOKUP(ConsolidadoPA[[#This Row],[MEDIDAS CONTRATO]],MedidasContrato[],3,0),"N/A")) | E23: =IF( ConsolidadoPA[[#This Row],[MEDIDAS CONTRATO]] = "", "", IFERROR( VLOOKUP(ConsolidadoPA[[#This Row],[MEDIDAS CONTRATO]],MedidasContrato[],4,0),"N/A")) | F23: =IF( ConsolidadoPA[[#This Row],[MEDIDAS CONTRATO]] = "", "", IFERROR( VLOOKUP(ConsolidadoPA[[#This Row],[MEDIDAS CONTRATO]],MedidasContrato[],5,0),"N/A")) | G23: =IFERROR( ConsolidadoPA[[#This Row],[A]]*ConsolidadoPA[[#This Row],[L]]*ConsolidadoPA[[#This Row],[P]], "") | I23: =IFERROR( ConsolidadoPA[[#This Row],[cm³ = V1]]/ConsolidadoPA[[#This Row],[cm³ = V2]],"") | N23: =IF( ConsolidadoPA[[#This Row],[QUAm-1]]="","",Consolidado!$M23+Consolidado!$J23-Consolidado!$L23-Consolidado!$K23) | O23: =IF(ConsolidadoPA[[#This Row],[FC = V1/V2]]="","",ConsolidadoPA[[#This Row],[FC = V1/V2]]*ConsolidadoPA[[#This Row],[QUAm]]) | P23: =IF( ConsolidadoPA[[#This Row],[Contrato]] = "", "", IFERROR( VLOOKUP(ConsolidadoPA[[#This Row],[Contrato]],TabelaPA[[Linha de Serviço PPU]:[PREÇO UNITÁRIO ]],3,0),"Nao Encontrado")) | Q23: =IF(ConsolidadoPA[[#This Row],[$ Unitário]]="","",Consolidado!$P23*Consolidado!$O23)
C24: =IF(ConsolidadoPA[[#This Row],[MEDIDAS CONTRATO]]="","", IFERROR( VLOOKUP(ConsolidadoPA[[#This Row],[MEDIDAS CONTRATO]],MedidasContrato[[MEDIDAS CONTRATO]:[Ø]],2,0),"N/A")) | D24: =IF( ConsolidadoPA[[#This Row],[MEDIDAS CONTRATO]] = "", "", IFERROR( VLOOKUP(ConsolidadoPA[[#This Row],[MEDIDAS CONTRATO]],MedidasContrato[],3,0),"N/A")) | E24: =IF( ConsolidadoPA[[#This Row],[MEDIDAS CONTRATO]] = "", "", IFERROR( VLOOKUP(ConsolidadoPA[[#This Row],[MEDIDAS CONTRATO]],MedidasContrato[],4,0),"N/A")) | F24: =IF( ConsolidadoPA[[#This Row],[MEDIDAS CONTRATO]] = "", "", IFERROR( VLOOKUP(ConsolidadoPA[[#This Row],[MEDIDAS CONTRATO]],MedidasContrato[],5,0),"N/A")) | G24: =IFERROR( ConsolidadoPA[[#This Row],[A]]*ConsolidadoPA[[#This Row],[L]]*ConsolidadoPA[[#This Row],[P]], "") | I24: =IFERROR( ConsolidadoPA[[#This Row],[cm³ = V1]]/ConsolidadoPA[[#This Row],[cm³ = V2]],"") | N24: =IF( ConsolidadoPA[[#This Row],[QUAm-1]]="","",Consolidado!$M24+Consolidado!$J24-Consolidado!$L24-Consolidado!$K24) | O24: =IF(ConsolidadoPA[[#This Row],[FC = V1/V2]]="","",ConsolidadoPA[[#This Row],[FC = V1/V2]]*ConsolidadoPA[[#This Row],[QUAm]]) | P24: =IF( ConsolidadoPA[[#This Row],[Contrato]] = "", "", IFERROR( VLOOKUP(ConsolidadoPA[[#This Row],[Contrato]],TabelaPA[[Linha de Serviço PPU]:[PREÇO UNITÁRIO ]],3,0),"Nao Encontrado")) | Q24: =IF(ConsolidadoPA[[#This Row],[$ Unitário]]="","",Consolidado!$P24*Consolidado!$O24)
C25: =IF(ConsolidadoPA[[#This Row],[MEDIDAS CONTRATO]]="","", IFERROR( VLOOKUP(ConsolidadoPA[[#This Row],[MEDIDAS CONTRATO]],MedidasContrato[[MEDIDAS CONTRATO]:[Ø]],2,0),"N/A")) | D25: =IF( ConsolidadoPA[[#This Row],[MEDIDAS CONTRATO]] = "", "", IFERROR( VLOOKUP(ConsolidadoPA[[#This Row],[MEDIDAS CONTRATO]],MedidasContrato[],3,0),"N/A")) | E25: =IF( ConsolidadoPA[[#This Row],[MEDIDAS CONTRATO]] = "", "", IFERROR( VLOOKUP(ConsolidadoPA[[#This Row],[MEDIDAS CONTRATO]],MedidasContrato[],4,0),"N/A")) | F25: =IF( ConsolidadoPA[[#This Row],[MEDIDAS CONTRATO]] = "", "", IFERROR( VLOOKUP(ConsolidadoPA[[#This Row],[MEDIDAS CONTRATO]],MedidasContrato[],5,0),"N/A")) | G25: =IFERROR( ConsolidadoPA[[#This Row],[A]]*ConsolidadoPA[[#This Row],[L]]*ConsolidadoPA[[#This Row],[P]], "") | I25: =IFERROR( ConsolidadoPA[[#This Row],[cm³ = V1]]/ConsolidadoPA[[#This Row],[cm³ = V2]],"") | N25: =IF( ConsolidadoPA[[#This Row],[QUAm-1]]="","",Consolidado!$M25+Consolidado!$J25-Consolidado!$L25-Consolidado!$K25) | O25: =IF(ConsolidadoPA[[#This Row],[FC = V1/V2]]="","",ConsolidadoPA[[#This Row],[FC = V1/V2]]*ConsolidadoPA[[#This Row],[QUAm]]) | P25: =IF( ConsolidadoPA[[#This Row],[Contrato]] = "", "", IFERROR( VLOOKUP(ConsolidadoPA[[#This Row],[Contrato]],TabelaPA[[Linha de Serviço PPU]:[PREÇO UNITÁRIO ]],3,0),"Nao Encontrado")) | Q25: =IF(ConsolidadoPA[[#This Row],[$ Unitário]]="","",Consolidado!$P25*Consolidado!$O25)

Sheet Tabela
A1: Padrão | C1: Tabela | E1: Linha de serviço PPU | G1: ITEM | H1: DESCRIÇÃO | I1: Linha de Serviço PPU | J1: UNID. | K1: PREÇO UNITÁRIO | L1: Descrição da Linha de Serviço | N1: MEDIDAS CONTRATO | O1: Ø | P1: A | Q1: L | R1: P
A2: Arquivo de aço 1 | C2: FC1 | E2: ARM-CX-DOC | G2: 1.1 | H2: ARM-CX-DOC: Armazenamento de caixas para documentos | I2: ARM-CX-DOC | J2: UA | K2: 0.9 | L2: Armazenamento de caixas para documentos | N2: A 0,5 X L 12,5 X P14,0 | P2: 0.5 | Q2: 12.5 | R2: 14
A3: Arquivo de aço 2 | C3: FC2 | E3: ARM-CX-MID | G3: 1.2 | H3: ARM-CX-MID: Armazenamento de caixas para mídias | I3: ARM-CX-MID | J3: UA | K3: 0.9 | L3: Armazenamento de caixas para mídias | N3: A 0,5 X L 13,0 X P13,0 | P3: 0.5 | Q3: 13 | R3: 13
A4: Arquivo de aço 3 | C4: FC3 | E4: ARM-TB | G4: 1.3 | H4: ARM-TB: Armazenamento de tubos | I4: ARM-TB | J4: UA | K4: 0.9 | L4: Armazenamento de tubos | N4: A 0,5 X L 14,0 X P 12,5 | P4: 0.5 | Q4: 14 | R4: 12.5
A5: Arquivo de aço 4 | C5: FC4 | E5: ARM-MA | G5: 1.4 | H5: ARM-MA: Armazenamento de mapotecas e arquivos de aço | I5: ARM-MA | J5: UA | K5: 70 | L5: Armazenamento de mapotecas e arquivos de aço | N5: A 0,5 X L 14,0 X P 13,0 | P5: 0.5 | Q5: 14 | R5: 13
A6: Arquivo de aço 5 | C6: FC5 | E6: ARM-MIC | G6: 1.5 | H6: ARM-MIC: Armazenamento de microformas | I6: ARM-MIC | J6: UA | K6: 0.1 | L6: Armazenamento de microformas | N6: A 0,5 X L 14,0 X P 14,0 | P6: 0.5 | Q6: 14 | R6: 14
A7: Caixa 10 kg (Jumbo) | C7: FC6 | E7: ARM-MID | G7: 1.6 | H7: ARM-MID: Armazenamento de midias | I7: ARM-MID | J7: UA | K7: 0.1 | L7: Armazenamento de midias | N7: A 08,0 X L 41,0 X P 41,0 | P7: 8 | Q7: 41 | R7: 41
A8: Caixa 20 Kg | C8: FC7 | E8: FRE-NRM | G8: 1.7 | H8: FRE-NRM: Frete normal | I8: FRE-NRM | J8: Frete | K8: 50 | L8: Frete normal | N8: A 1,0 X L 12,5 X P14,0 | P8: 1 | Q8: 12.5 | R8: 14
A9: Caixa 20 kg - Tipo 1 | C9: FC8 | E9: FRE-EXP | G9: 1.8 | H9: FRE-EXP: Frete expresso | I9: FRE-EXP | J9: Frete | K9: 100 | L9: Frete expresso | N9: A 1,0 X L 14,0 X P 13,0 | P9: 1 | Q9: 14 | R9: 13
A10: Caixa 20 kg - Tipo 2 | C10: FC9 | E10: INS-ITEM | G10: 1.9 | H10: KM-AD: Quilometragem adicional | I10: KM-AD | J10: KM | K10: 1 | L10: Quilometragem adicional | N10: A 1,0 X L 14,0 X P 19,0 | P10: 1 | Q10: 14 | R10: 19
A11: Caixa 20 kg (contendo Mídias e Microfilmes) | E11: PES-ITEM | G11: 1.10 | H11: PES-ITEM: Pesquisa de itens avulsos | I11: PES-ITEM | J11: Item Avulso | K11: 3 | L11: Pesquisa de itens avulsos | N11: A 10,0 X L 10,0 X P 2,5 | P11: 10 | Q11: 10 | R11: 2.5
A12: Caixa 5 kg | E12: DES-EMB | G12: 1.11 | H12: DES-EMB: Destruição segura de documentos | I12: DES-EMB | J12: Embalagem | K12: 3 | L12: Destruição segura de documentos | N12: A 10,0 X L 10,5 X P 4,0 | P12: 10 | Q12: 10.5 | R12: 4
A13: Caixa 5kg | E13: TRANSF | G13: 1.12 | H13: TRANSF: Transferência inicial de acervo documental | I13: TRANSF | J13: Transferência | K13: 100000 | L13: Transferência inicial de acervo documental | N13: A 10,0 X L 15,5 X P 0,3 | P13: 10 | Q13: 15.5 | R13: 0.3
A14: Caixa 7 kg | E14: MIGR-UA | G14: 1.13 | H14: MIGR-UA: Migração de acervo documental para digitalização | I14: MIGR-UA | J14: UA | K14: 7.5 | L14: Migração de acervo documental para digitalização | N14: A 10,0 X L 19,0 X P 26,5 | P14: 10 | Q14: 19 | R14: 26.5
A15: Caixa para mídias - Tipo 1 | E15: CAT-EMB | G15: 2.1 | H15: CAT-ITEM: Catalogação de documentos digitalizados | I15: CAT-ITEM | J15: Documento | K15: 0.2 | L15: Catalogação de documentos digitalizados | N15: A 10,0 X L 3,0 X P 10,0 | P15: 10 | Q15: 3 | R15: 10
A16: Caixa para mídias - Tipo 2 | E16: CAT-ITEM | G16: 2.2 | H16: ORG-DOC: Organização de documentos para digitalização | I16: ORG-DOC | J16: UA | K16: 10 | L16: Organização de documentos para digitalização | N16: A 10,0 X L 4,5 X P 10,0 | P16: 10 | Q16: 4.5 | R16: 10
A17: Documentação administrativa | E17: ORG-DOC | G17: 2.3 | H17: DIG-MI: Digitalização de microfilmes | I17: DIG-MI | J17: UD | K17: 0.05 | L17: Digitalização de microfilmes | N17: A 10,5 X L 15,0 X P 0,3 | P17: 10.5 | Q17: 15 | R17: 0.3
A18: Documentação bibliográfica | E18: HIG-MI | G18: 2.4 | H18: DIG-MF: Digitalização de microfichas | I18: DIG-MF | J18: UD | K18: 0.05 | L18: Digitalização de microfichas | N18: A 10,5 X L 19,0 X P2,5 | P18: 10.5 | Q18: 19 | R18: 2.5
A19: Documentação contábil e financeira | E19: HIG-MF | G19: 2.5 | H19: DIG-DOC: Digitalização de documentos | I19: DIG-DOC | J19: UD | K19: 0.11 | L19: Digitalização de documentos | N19: A 10,5 X L 41,0 X P 41,0 | P19: 10.5 | Q19: 41 | R19: 41
A20: Documentação contratual | E20: HIG-PER | G20: 2.6 | H20: IND-DOC: Indexação de documentos | I20: IND-DOC | J20: UD | K20: 0.1 | L20: Indexação de documentos | N20: A 100,0 X L 140,0 X P 51,0 | P20: 100 | Q20: 140 | R20: 51
A21: Documentação técnica | E21: DIG-MI | G21: 2.7 | H21: CONV-MID: Conversão de mídias | I21: CONV-MID | J21: Mídia | K21: 40 | L21: Conversão de mídias | N21: A 11,0 X L 15,5 X P 0,3 | P21: 11 | Q21: 15.5 | R21: 0.3
A22: Documento - Formato A0 | E22: DIG-MF | G22: 2.8 | H22: GRV-MID: Gravação de mídias | I22: GRV-MID | J22: Mídia | K22: 40 | L22: Gravação de mídias | N22: A 11,0 X L 33,0 X P 37,0 | P22: 11 | Q22: 33 | R22: 37
A23: Documento - Formato A1 | E23: DIG-DOC | G23: 2.9 | H23: COP-MID: Cópia de mídias | I23: COP-MID | J23: Mídia | K23: 5 | L23: Cópia de mídias | N23: A 11,0 X L 33,0 X P 41,0 | P23: 11 | Q23: 33 | R23: 41
A24: Documento - Formato A2 | E24: IND-DOC | N24: A 11,5 X L 37,0 X P 33,0 | P24: 11.5 | Q24: 37 | R24: 33
A25: Documento - Formato A3 | E25: CONV-MID | N25: A 12,0 X L 34,0 X P 37,0 | P25: 12 | Q25: 34 | R25: 37
A26: Documento - Formato A4 | E26: GRV-MID | N26: A 12,0 X L 34,0 X P 37,0 | P26: 12 | Q26: 34 | R26: 37
A27: Documento - Superior ao Formato A0 | E27: COP-MID | N27: A 12,5 X L 14 X P 0,5 | P27: 12.5 | Q27: 14 | R27: 0.5
A28: Embalagem | E28: COP-VID | N28: A 12,5 X L 14,5 X P0,5 | P28: 12.5 | Q28: 14.5 | R28: 0.5
A29: Fita VHS | E29: N/A | N29: A 130,0 X L 060,0 X P 72,0 | P29: 130 | Q29: 60 | R29: 72
A30: Item avulso | N30: A 130,0 X L 060,0 X P 73,0 | P30: 130 | Q30: 60 | R30: 73
A31: Item documental | N31: A 135,0 X L 51,0 X P 105,0 | P31: 135 | Q31: 51 | R31: 105
A32: Item documental em caixa | N32: A 140,0 X L 067,0 X P 72,0 | P32: 140 | Q32: 67 | R32: 72
A33: Item documental em mapoteca | N33: A 15,0 X L 40,0 X P 35,0 | P33: 15 | Q33: 40 | R33: 35
A34: Item documental em Tubo | N34: A 150,0 X L 090,0 X P 76,0 | P34: 150 | Q34: 90 | R34: 76
A35: Kit de material | N35: A 16,5 X L 11,5 X P 0,3 | P35: 16.5 | Q35: 11.5 | R35: 0.3
A36: Mapoteca | N36: A 17,0 X L 20,5 X P 111,5 | P36: 17 | Q36: 20.5 | R36: 111.5
A37: Microficha | N37: A 170,0 X L 061,0 X P 72,0 | P37: 170 | Q37: 61 | R37: 72
A38: Microfilme | N38: A 180,0 X L 068,0 X P 72,0 | P38: 180 | Q38: 68 | R38: 72
A39: Microfilme 16 mm | N39: A 21,0 X L 31,0 X P 46,0 | P39: 21 | Q39: 31 | R39: 46
A40: Microfilme 35 mm | N40: A 21,0 X L 41,0 X P 55,0 | P40: 21 | Q40: 41 | R40: 55
A41: Microforma em arquivo de aço | N41: A 21,5 X L 41,0 X P 51,0 | P41: 21.5 | Q41: 41 | R41: 51
... A54: Tubo para perfil de poço | N54: A 26,5 X L 38,0 X P 45,5 | P54: 26.5 | Q54: 38 | R54: 45.5
N55: A 26,5 X L 38,5 X P 46,5 | P55: 26.5 | Q55: 38.5 | R55: 46.5
N56: A 26,5 X L 40,0 X P 49,0 | P56: 26.5 | Q56: 40 | R56: 49
N57: A 27,0 X L 36,0 X P 47,0 | P57: 27 | Q57: 36 | R57: 47
N58: A 27,0 X L 36,0 X P 49,0 | P58: 27 | Q58: 36 | R58: 49
N59: A 27,0 X L 38,0 X P 49,0 | P59: 27 | Q59: 38 | R59: 49
N60: A 27,5 X L 36,0 X P 49,0 | P60: 27.5 | Q60: 36 | R60: 49
N61: A 28,0 X L 37,5 X P 46,0 | P61: 28 | Q61: 37.5 | R61: 46
N62: A 28,0 X L 37,5 X P 47,5 | P62: 28 | Q62: 37.5 | R62: 47.5
N63: A 28,0 X L 37,5 X P 48,0 | P63: 28 | Q63: 37.5 | R63: 48
N64: A 28,0 X L 38,0 X P 46,5 | P64: 28 | Q64: 38 | R64: 46.5
N65: A 28,0 X L 38,5 X P 48,0 | P65: 28 | Q65: 38.5 | R65: 48
N66: A 28,0 X L 39,0 X P 46,0 | P66: 28 | Q66: 39 | R66: 46
... N86: A 34,0 X L 37,0 X P 12,0 | P86: 34 | Q86: 37 | R86: 12
N87: A 4,5 X L 10 | P87: 4.5 | Q87: 10
N88: A 40,5 X L 41,5 X P 10,0 | P88: 40.5 | Q88: 41.5 | R88: 10
N89: A 40,5 X L41,5 X P 10,0 | P89: 40.5 | Q89: 41.5 | R89: 10
N90: L 0,11 X C 1,20 | Q90: 0.11 | R90: 1.2
N91: L 0,11 X C 1,23 | Q91: 0.11 | R91: 1.23
N92: L 0,11 X C 1,26 | Q92: 0.11 | R92: 1.26
N93: L 0,11 X C 1,30 | Q93: 0.11 | R93: 1.3
N94: L 05,0 X A 35,0 | P94: 35 | Q94: 5
N95: L 05,0 X A 36,0 | P95: 36 | Q95: 5
N96: L 05,0 X A 47,0 | P96: 47 | Q96: 5
N97: L 06,0 X A 45,0 | P97: 45 | Q97: 6
N98: L 07,0 X A 64,0 | P98: 64 | Q98: 7
N99: L 07,0 X A 66,0 | P99: 66 | Q99: 7
N100: L 07,0 X A 88,0 | P100: 88 | Q100: 7
N101: L 07,5 X A 54,0 | P101: 54 | Q101: 7.5
N102: L 09,0 X A 70,0 | P102: 70 | Q102: 9
N103: L 09,0 X A 93,0 | P103: 93 | Q103: 9
N104: L 09,5 X A 94,0 | P104: 94 | Q104: 9.5
N105: L 10 X P 30 | P105: 104 | Q105: 10 | R105: 30
N106: L 10,0 X A 104,0 | P106: 120 | Q106: 10
N107: L 10,0 X A 120,0 | P107: 76 | Q107: 10
N108: L 10,0 X A 76,0 | P108: 92 | Q108: 10
N109: L 10,0 X A 92,0 | Q109: 10
N110: L 10,0 X P 122,0 | Q110: 10 | R110: 122
N111: L 10,0 X P 124,0 | Q111: 10 | R111: 124
N112: L 10,0 X P 125,0 | Q112: 10 | R112: 125
N113: L 10,0 X P 130,0 | Q113: 10 | R113: 130
N114: L 10,0 X P 30,0 | Q114: 10 | R114: 30
N115: L 10,5 X P 100,0 | Q115: 10.5 | R115: 100
N116: L 11,0 X P 122,0 | Q116: 11 | R116: 122
N117: L 16,0 X A 96,0 | P117: 96 | Q117: 16
N118: L 6,0 X P 152,0 | Q118: 6 | R118: 152
N119: L 6,0 X P 71,0 | Q119: 6 | R119: 71
N120: L 6,0 X P 81,0 | Q120: 6 | R120: 81
N121: L 7,0 X P 100,0 | Q121: 7 | R121: 100
N122: L 7,0 X P 120,0 | Q122: 7 | R122: 120
N123: L 9,0 X P 93,0 | Q123: 9 | R123: 93
N124: Ø10,0 P 120,0 | O124: 10 | R124: 120

Sheet Mapa Geral
A1: Nº Da Ordem | B1: Medição | C1: Service Now | D1: Quantidade Service Now | E1: Unidade de atendimento | F1: UF para atendimento | G1: Demandante | H1: Telefone | I1: Gerência | J1: Data de emissão | K1: Data máxima de atendimento | L1: Data de atendimento | M1: Data de envio da O.S | N1: Status do Prazo | O1: Linha de serviço | P1: Tipo de Solicitação | Q1: Caixa de 20 Kg | R1: Caixa de Mídia | S1: Tubo de Engenharia | T1: Tubo de perfil de poços | U1: Etiqueta de caixa | V1: Lacre | W1: Observações | X1: Endereço de atendimento | Y1: Grupo | Z1: KM
A2: 0008/2026 | B2: 26/06/2026 a 25/07/2026 | C2: CSC0788409 | D2: 3 | F2: BA | G2: NÃO INFORMADO | I2: SUPRIMENTOS RMF RDR | J2: 46163 | K2: 46164 | L2: 46206 | N2: NÃO | O2: Pesquisa | P2: Normal
A3: 0014/2026 | B3: 26/06/2026 a 25/07/2026 | C3: NÃO INFORMADO | D3: 159 | F3: BA | G3: NÃO INFORMADO | I3: NÃO INFORMADO | J3: 46189 | K3: 46190 | L3: 46206 | N3: SIM | O3: Pesquisa | P3: Normal
A4: 0018/2026 | B4: 26/06/2026 a 25/07/2026 | C4: NÃO INFORMADO | D4: 11 | F4: BA | G4: NÃO INFORMADO | I4: NÃO INFORMADO | J4: 46199 | K4: 46202 | L4: 46199 | N4: SIM | O4: Pesquisa | P4: Normal
A5: 0019/2026 | B5: 26/06/2026 a 25/07/2026 | C5: CSC0811201 | D5: 10 | F5: BA | G5: Jose Paulo de Jesus Santos Departamento | I5: SMS SA SAO DENGE-DPI-DLCM-DTEN | J5: 46199 | K5: 46202 | L5: 46199 | N5: SIM | O5: Pesquisa | P5: Normal
A6: 0020/2026 | B6: 26/06/2026 a 25/07/2026 | C6: CSC0824264 | D6: 1 | F6: BA | G6: NÃO INFORMADO | I6: RH RBO COA CB | J6: 46199 | K6: 46202 | L6: 46202 | N6: SIM | O6: Pesquisa | P6: Normal
A7: 0021/2026 | B7: 26/06/2026 a 25/07/2026 | C7: CSC0829650 | D7: 10 | F7: BA | G7: Jose Paulo de Jesus Santos | I7: SMS SA SAO DENGE-DPI-DLCM-DTEN | J7: 46199 | K7: 46202 | L7: 46202 | N7: SIM | O7: Pesquisa | P7: Normal
A8: 0022/2026 | B8: 26/06/2026 a 25/07/2026 | C8: CSC0831386 | D8: 13 | F8: BA | G8: Jose Paulo de Jesus Santos | I8: SMS SA SAO DENGE-DPI-DLCM-DTEN | J8: 46204 | K8: 46206 | L8: 46204 | N8: SIM | O8: Pesquisa | P8: Normal
A9: 0023/2026 | B9: 26/06/2026 a 25/07/2026 | C9: CSC0783878 | D9: 1 | F9: BA | G9: NÃO INFORMADO | I9: NÃO INFORMADO | J9: 46206 | K9: 46209 | L9: 46206 | N9: SIM | O9: Pesquisa | P9: Normal
A10: 0024/2026 | B10: 26/06/2026 a 25/07/2026 | C10: CSC0819994 | D10: 9 | F10: BA | G10: Jose Paulo de Jesus Santos | I10: SMS SA SAO DENGE-DPI-DLCM-DTEN | J10: 46206 | K10: 46209 | L10: 46209 | N10: SIM | O10: Pesquisa | P10: Normal
A11: 0025/2026 | B11: 26/06/2026 a 25/07/2026 | C11: CSC0820439 | D11: 6 | F11: BA | G11: Jose Paulo de Jesus Santos | I11: SMS SA SAO DENGE-DPI-DLCM-DTEN | J11: 46206 | K11: 46209 | L11: 46223 | N11: NÃO | O11: Pesquisa | P11: Normal
A12: 0026/2026 | B12: 26/06/2026 a 25/07/2026 | C12: CSC0808892 | D12: 1 | F12: BA | G12: Thallya Vitoria Souza | I12: SMS SA SAO STO | J12: 46206 | K12: 46209 | L12: 46220 | N12: NÃO | O12: Pesquisa | P12: Normal
A13: 0027/2026 | B13: 26/06/2026 a 25/07/2026 | C13: CSC0810976 | D13: 10 | F13: BA | G13: Jose Paulo de Jesus Santos | I13: SMS SA SAO DENGE-DPI-DLCM-DTEN | J13: 46206 | K13: 46209 | L13: 46221 | N13: NÃO | O13: Pesquisa | P13: Normal
... A26: 0041/2026 | B26: 26/06/2026 a 25/07/2026 | C26: CSC0849777 | D26: 1 | F26: BA | G26: Thallya Vitoria Souza | I26: SMS SA SAO STO | J26: 46225 | K26: 46226 | L26: 46225 | N26: SIM | O26: Pesquisa | P26: Normal
A27: 0024/2026 | B27: 26/06/2026 a 25/07/2026 | C27: CSC0827133 / CSC0827142 / CSC0827170 | D27: 5 | E27: RNEST | F27: PE | G27: Aline Larissa dos Santos Agostinho | H27: 81 99560-6225 | I27: RNEST/SMS/SSO | J27: 46196 | K27: 46203 | L27: 46211 | M27: 46211 | N27: NÃO | O27: Implantação | P27: Normal | Y27: B | Z27: 746
A28: 0026/2026 | B28: 26/06/2026 a 25/07/2026 | C28: CSC0830441 / CSC0830445 | D28: 11 | E28: RNEST | F28: PE | G28: Aline Larissa dos Santos Agostinho | H28: 81 99560-6225 | I28: RNEST/SMS/SSO | J28: 46203 | K28: 46205 | L28: 46211 | M28: 46211 | N28: NÃO | O28: Implantação | P28: Normal | Y28: B | Z28: 746
A29: 0027/2026 | B29: 26/06/2026 a 25/07/2026 | C29: CSC0846380 | D29: 22 | E29: EDIRN | F29: RN | G29: Nayra Kallyne de Brito Araujo / Malkene | H29: (84) 84 999174758 / 84 98894-2932 | I29: SMS/LMA/GAE&P/AM-RN-CE | J29: 46223 | K29: 46226 | L29: 46226 | M29: 46226 | N29: SIM | O29: Implantação | P29: Normal | Y29: C | Z29: 1058
A30: 0029/2026 | B30: 26/06/2026 a 25/07/2026 | C30: CSC0847315 | D30: 9 | E30: EDIRN | F30: RN | G30: Malkene Wytiza Freire de Medeiros Noronha | H30: (84) 98894-2932 | I30: TAR/PC/REC | J30: 46223 | K30: 46226 | L30: 46226 | M30: 46227 | N30: SIM | O30: Implantação | P30: Normal | Y30: C | Z30: 1058
A31: 0030/2026 | B31: 26/06/2026 a 25/07/2026 | C31: CSC0847436 | D31: 1 | E31: UTE-BAHIA | F31: BA | G31: Adriana Silvana Ferreira / Caetano | H31: (71) 98757-1027 / 71 98749-0368 | I31: G&E/TERM/UTE-TBA | J31: 46223 | K31: 46227 | L31: 46227 | M31: 46227 | N31: NÃO | O31: Implantação | P31: Normal | Y31: A | Z31: 46
A32: 0026/2026 | B32: 26/06/2026 a 25/07/2026 | C32: CSC0846393 | D32: 50 | E32: EDIRN | F32: RN | G32: Malkene Wytiza Freire de Medeiros Noronha | H32: (84) 98894-2932 | I32: TAR/PC/REC | J32: 46220 | K32: 46225 | L32: 46226 | M32: 46226 | N32: NÃO | O32: Materiais | P32: Normal | Q32: 50 | U32: 100 | V32: 50 | X32: AV. EUZÉBIO ROCHA, 1000, CIDADE DA ESPERANÇA, NATAL-RN, CEP: 59070-900. | Y32: C | Z32: 1058
A33: 0027/2027 | B33: 26/06/2026 a 25/07/2026 | C33: CSC0847689 | D33: 80 | E33: C.T. SSEBPASSÉ | F33: BA | G33: Iuri Santana Amadeu | H33: 71992764349 | I33: COMPARTILHADO/SC/SID | J33: 46223 | K33: 46225 | L33: 46225 | N33: SIM | O33: Materiais | P33: Normal | Q33: 80 | W33: Material não recebido pela Petrobras/Cancelado sem aviso | X33: Campo de Taquipe, S/N , São Sebastião Passe | Y33: A | Z33: 44
H38: Grupo 1 | J38: Grupo 2
G39: ANALISES | H39: Qtd | I39: % | J39: Qtd | K39: %
G40: Total de ordens de serviço ATENDIDAS | H40: 6 | I40: 1 | J40: 25 | K40: 1
G41: Total de orden de serviço NO PRAZO | H41: 2 | I41: =H41/H40 -> 0.33333333 | J41: 19 | K41: =J41/J40 -> 0.76
G42: Total de orden de serviço FORA DOPRAZO | H42: =H40-H41 -> 4 | I42: =H42/H40 -> 0.66666667 | J42: =J40-J41 -> 6 | K42: =J42/J41 -> 0.31578947

Sheet Digitalização Click
A1: Nº Da Ordem | B1: Service Now | C1: Unidade de atendimento | D1: Dada abertura da OS | E1: Tipo do Prazo | F1: Excedeu volume | G1: SLA | H1: Data limite de atendimento | I1: Data de início do processo | J1: Data final do processo | K1: Data de entrega das imagens | L1: Prazo | M1: Caixa PA | N1: Caixa Cliente | O1: Qtd de documentos | P1: Qtd de documentos indexados | Q1: Qtd de documentos catalogados | R1: Qtd de Imagens | S1: Quantidade x FC | T1: Tipo documental | U1: Documento | V1: FC | W1: Parcionamento | X1: Qtd parcionamento | Y1: Gerência | Z1: Solicitante
A2: 0008/2026 | B2: CSC0788409 | C2: BA | D2: 46163 | E2: NORMAL | F2: NÃO | G2: D+1 | H2: 46164 | K2: 46206 | L2: NÃO | M2: BA3-3003-I-013 | N2: CX0012000045921SOS CX00120G70394681SOS CX00120G70402395SOS CX00120G70447636SOS CX00120G70447700SOS CX00120G70508196SOS CX00120G70508204SOS CX00120G100548776SOS CX00120G100548778SOS CX00120G100548781SOS CX00120G100548793SOS CX00120G100548802SOS CX00120G100548805SOS | O2: 3 | P2: 3 | Q2: 3 | R2: 486 | S2: =Table_3[[#This Row],[Qtd de Imagens]]*Table_3[[#This Row],[FC]] -> 486 | T2: TECNICA | U2: A4 | V2: 1 | W2: NÃO | X2: 0 | Y2: SUPRIMENTOS RMF RDR | Z2: NÃO INFORMADO
A3: 0014/2026 | B3: NÃO INFORMADO | C3: BA | D3: 46189 | E3: NORMAL | F3: SIM | G3: D+1 | H3: 46190 | K3: 46206 | L3: SIM | M3: EM TRANSFERENCIA | N3: CX00120G100548805SOS CX00120G100548793SOS CX00120G100548781SOS CX00120G100548778SOS CX00120G100548776SOS CX00120G70508204SOS CX00120G70508196SOS CX00120G70402395SOS | O3: 159 | P3: 159 | Q3: 159 | R3: 13909 | S3: =Table_3[[#This Row],[Qtd de Imagens]]*Table_3[[#This Row],[FC]] -> 13909 | T3: TECNICA | U3: A4 | V3: 1 | W3: NÃO | X3: 0 | Y3: NÃO INFORMADO | Z3: NÃO INFORMADO
A4: 0018/2026 | B4: NÃO INFORMADO | C4: BA | D4: 46199 | E4: NORMAL | F4: NÃO | G4: D+1 | H4: 46202 | K4: 46199 | L4: SIM | M4: EM TRANSFERENCIA | N4: CX00120G70413279SOS | O4: 11 | P4: 11 | Q4: 11 | R4: 709 | S4: =Table_3[[#This Row],[Qtd de Imagens]]*Table_3[[#This Row],[FC]] -> 709 | T4: PRONTUARIO MEDICO | U4: A4 | V4: 1 | W4: NÃO | X4: 0 | Y4: NÃO INFORMADO | Z4: NÃO INFORMADO
A5: 0019/2026 | B5: CSC0811201 | C5: BA | D5: 46199 | E5: NORMAL | F5: SIM | G5: D+1 | H5: 46202 | K5: 46199 | L5: SIM | M5: EM TRANSFERENCIA | N5: CX00120G70413266SOS | O5: 10 | P5: 10 | Q5: 10 | R5: 760 | S5: =Table_3[[#This Row],[Qtd de Imagens]]*Table_3[[#This Row],[FC]] -> 760 | T5: PRONTUARIO MEDICO | U5: A4 | V5: 1 | W5: NÃO | X5: 0 | Y5: SMS SA SAO DENGE-DPI-DLCM-DTEN | Z5: Jose Paulo de Jesus Santos Departamento
A6: 0020/2026 | B6: CSC0824264 | C6: BA | D6: 46199 | E6: NORMAL | F6: NÃO | G6: D+1 | H6: 46202 | K6: 46202 | L6: SIM | M6: BA3-3010-F-102 | N6: CX00120G70265450SOS | O6: 1 | P6: 1 | Q6: 1 | R6: 7 | S6: =Table_3[[#This Row],[Qtd de Imagens]]*Table_3[[#This Row],[FC]] -> 7 | T6: RH | U6: A4 | V6: 1 | W6: NÃO | X6: 0 | Y6: RH RBO COA CB | Z6: NÃO INFORMADO
A7: 0021/2026 | B7: CSC0829650 | C7: BA | D7: 46199 | E7: NORMAL | F7: NÃO | G7: D+1 | H7: 46202 | K7: 46202 | L7: SIM | M7: BA3-3014-G-036 | N7: CX00120G100543696SOS | O7: 10 | P7: 10 | Q7: 10 | R7: 692 | S7: =Table_3[[#This Row],[Qtd de Imagens]]*Table_3[[#This Row],[FC]] -> 692 | T7: PRONTUARIO MEDICO | U7: A4 | V7: 1 | W7: NÃO | X7: 0 | Y7: SMS SA SAO DENGE-DPI-DLCM-DTEN | Z7: Jose Paulo de Jesus Santos
A8: 0022/2026 | B8: CSC0831386 | C8: BA | D8: 46204 | E8: NORMAL | F8: NÃO | G8: D+1 | H8: 46206 | K8: 46204 | L8: SIM | M8: EM TRANSFERENCIA | N8: CX00120G70391882SOS | O8: 13 | P8: 13 | Q8: 13 | R8: 1040 | S8: =Table_3[[#This Row],[Qtd de Imagens]]*Table_3[[#This Row],[FC]] -> 1040 | T8: PRONTUARIO MEDICO | U8: A4 | V8: 1 | W8: NÃO | X8: 0 | Y8: SMS SA SAO DENGE-DPI-DLCM-DTEN | Z8: Jose Paulo de Jesus Santos
A9: 0023/2026 | B9: CSC0783878 | C9: BA | D9: 46206 | E9: NORMAL | F9: NÃO | G9: D+1 | H9: 46209 | K9: 46206 | L9: SIM | M9: BA3-3010-A-102 | N9: CX00120G70439250SOS | O9: 1 | P9: 1 | Q9: 1 | R9: 20 | S9: =Table_3[[#This Row],[Qtd de Imagens]]*Table_3[[#This Row],[FC]] -> 20 | T9: ADMINISTRATIVA | U9: A4 | V9: 1 | W9: NÃO | X9: 0 | Y9: NÃO INFORMADO | Z9: NÃO INFORMADO
A10: 0024/2026 | B10: CSC0819994 | C10: BA | D10: 46206 | E10: NORMAL | F10: NÃO | G10: D+1 | H10: 46209 | K10: 46209 | L10: SIM | M10: BA3-3014-G-031 | N10: CX00120G100543699SOS | O10: 9 | P10: 9 | Q10: 9 | R10: 922 | S10: =Table_3[[#This Row],[Qtd de Imagens]]*Table_3[[#This Row],[FC]] -> 922 | T10: PRONTUARIO MEDICO | U10: A4 | V10: 1 | W10: NÃO | X10: 0 | Y10: SMS SA SAO DENGE-DPI-DLCM-DTEN | Z10: Jose Paulo de Jesus Santos
A11: 0025/2026 | B11: CSC0820439 | C11: BA | D11: 46206 | E11: NORMAL | F11: NÃO | G11: D+1 | H11: 46209 | K11: 46223 | L11: NÃO | M11: EM TRANSFERENCIA | N11: CX00120G100543713SOS | O11: 6 | P11: 6 | Q11: 6 | R11: 591 | S11: =Table_3[[#This Row],[Qtd de Imagens]]*Table_3[[#This Row],[FC]] -> 591 | T11: PRONTUARIO MEDICO | U11: A4 | V11: 1 | W11: NÃO | X11: 0 | Y11: SMS SA SAO DENGE-DPI-DLCM-DTEN | Z11: Jose Paulo de Jesus Santos
A12: 0026/2026 | B12: CSC0808892 | C12: BA | D12: 46206 | E12: NORMAL | F12: NÃO | G12: D+1 | H12: 46209 | K12: 46220 | L12: NÃO | M12: BA3-3008-G-008 | N12: CX00120G70265424SOS | O12: 1 | P12: 1 | Q12: 1 | R12: 1 | S12: =Table_3[[#This Row],[Qtd de Imagens]]*Table_3[[#This Row],[FC]] -> 1 | T12: PRONTUARIO MEDICO | U12: A4 | V12: 1 | W12: NÃO | X12: 0 | Y12: SMS SA SAO STO | Z12: Thallya Vitoria Souza
A13: 0027/2026 | B13: CSC0810976 | C13: BA | D13: 46206 | E13: NORMAL | F13: NÃO | G13: D+1 | H13: 46209 | K13: 46221 | L13: NÃO | M13: EM TRANSFERENCIA | N13: CX00120G70413252SOS | O13: 10 | P13: 10 | Q13: 10 | R13: 796 | S13: =Table_3[[#This Row],[Qtd de Imagens]]*Table_3[[#This Row],[FC]] -> 796 | T13: PRONTUARIO MEDICO | U13: A4 | V13: 1 | W13: NÃO | X13: 0 | Y13: SMS SA SAO DENGE-DPI-DLCM-DTEN | Z13: Jose Paulo de Jesus Santos
... A26: 0041/2026 | B26: CSC0849777 | C26: BA | D26: 46225 | E26: NORMAL | F26: NÃO | G26: D+1 | H26: 46226 | K26: 46225 | L26: SIM | M26: BA3-3008-G-008 | N26: CX00120G70265424SOS | O26: 1 | P26: 1 | Q26: 1 | R26: 1 | S26: =Table_3[[#This Row],[Qtd de Imagens]]*Table_3[[#This Row],[FC]] -> 1 | T26: PRONTUARIO MEDICO | U26: A4 | V26: 1 | W26: NÃO | X26: 0 | Y26: SMS SA SAO STO | Z26: Thallya Vitoria Souza
A29: Serviços | C29: BA
A30: Digitalização de Microfichas | C30: =SUMIF(U2:U26,"microficha",S2:S26) -> 51
A31: Indexação de documentos | C31: =SUM(O2:O26) -> 436
A32: Digitalização de documentos | C32: =SUM(S2:S26)-C30-C34-C335 -> 34544
A33: Digitalização UN_SEAL | C33: 0
A34: Upload de vídeos - Sob demanda | C34: 0 | D34: Cópia de Vídeos
A35: Upload de vídeos | C35: 0 | D35: Cópia de Vídeos
A36: Pesquisa de itens avulsos | C36: =SUM(Table_3[Qtd de documentos]) -> 436

Sheet Atendimentos
A1: OS | B1: Click | C1: Unidade de atendimento | D1: Data da OS | E1: Data máxima | F1: Data do atendimento | G1: Nível de Serviço | H1: SLA | I1: Frete a Cobrar | J1: Tipo | K1: Embalagem | L1: Item avulso | M1: Cálculo | N1: Endereço SOS | O1: Endereço Petrobras | P1: Distância SOS>Petrobras | Q1: Status | R1: Cobrar excedente | S1: Link

Sheet Digitalização Projeto
B2: Salvador Projeto digitalização Perfil de poços Taquipe | G2: Tamanho Total | H2: Tamanho x FC | I2: Indexação | J2: Retirada | K2: KM-Adicional
G3: =SUM(G7:G1590) -> 5688.82 | H3: =G3*13.45 -> 76514.629 | I3: 1584 | J3: 1584 | K3: 3
H4: =H3*0.14 -> 10712.048 | I4: =I3*0.7 -> 1108.8 | J4: =J3/60*25 -> 660 | K4: =K3*0.25 -> 0.75
B6: PERFIL | C6: CAMPO | D6: CAIXA | E6: CAIXA NOVA | F6: PERFIL | G6: LARG X COMPR (Metros) | H6: FATOR DE CONVERSÃO | I6: Total imagem | J6: Total Indexação R$
B7: 1-CON-001-BA | C7: TUCANO DO SUL | D7: CAIXA 01 | E7: N/A | F7: 1CON1_BPP_200_8.625_2002-03-21.pdf | G7: 2.92 | H7: 13.45 | I7: =G7*H7 -> 39.274 | J7: 1
B8: 1-CON-001-BA | C8: TUCANO DO SUL | D8: CAIXA 01 | E8: N/A | F8: 1CON1_CANHONEIO_CGEL_200_8.625_2002-03-21.pdf | G8: 3.55 | H8: 13.45 | I8: =G8*H8 -> 47.7475 | J8: 1
B9: 1-FSR-1-BA | C9: TUCANO DO SUL | D9: CAIXA 01 | E9: N/A | F9: 1FSR1_(ILEGIVEL) (1).pdf | G9: 2.54 | H9: 13.45 | I9: =G9*H9 -> 34.163 | J9: 1
B10: 1-FSR-1-BA | C10: TUCANO DO SUL | D10: CAIXA 01 | E10: N/A | F10: 1FSR1_(ILEGIVEL) (2).pdf | G10: 2.54 | H10: 13.45 | I10: =G10*H10 -> 34.163 | J10: 1
B11: 1-FSR-1-BA | C11: TUCANO DO SUL | D11: CAIXA 01 | E11: N/A | F11: 1FSR1_(ILEGIVEL) (3).pdf | G11: 2.22 | H11: 13.45 | I11: =G11*H11 -> 29.859 | J11: 1
B12: 1-FSR-1-BA | C12: TUCANO DO SUL | D12: CAIXA 01 | E12: N/A | F12: 1FSR1_(ILEGIVEL) (4).pdf | G12: 2.38 | H12: 13.45 | I12: =G12*H12 -> 32.011 | J12: 1
B13: 1-QE-1-BA | C13: TUCANO DO SUL | D13: CAIXA 01 | E13: N/A | F13: 1QE1_CASING_COLLAR_LOG_AND_PERFORATING_RECORD_1_200_1972-11-18.pdf | G13: 2 | H13: 13.45 | I13: =G13*H13 -> 26.9 | J13: 1
B14: 3-CON-4-BA | C14: TUCANO DO SUL | D14: CAIXA 01 | E14: N/A | F14: 3CON4_MICROPERFIL_1_200_12.250_1968-02-19.pdf | G14: 2.39 | H14: 13.45 | I14: =G14*H14 -> 32.1455 | J14: 1
B15: 3-CON-4-BA | C15: TUCANO DO SUL | D15: CAIXA 01 | E15: N/A | F15: 3CON4_MICROPERFIL_2_200_8.500_1969-03-16.pdf | G15: 4.8 | H15: 13.45 | I15: =G15*H15 -> 64.56 | J15: 1
B16: 3-CON-4-BA | C16: TUCANO DO SUL | D16: CAIXA 01 | E16: N/A | F16: 3CON4_MICROPERFIL_2_200_9.625_1969-03-16.pdf | G16: 3.7 | H16: 13.45 | I16: =G16*H16 -> 49.765 | J16: 1
B17: 3-CON-5-BA | C17: TUCANO DO SUL | D17: CAIXA 01 | E17: N/A | F17: 3CON5_CASING_COLLAR_LOG_AND_PERFORATING_RECORD_2_200_8.625_1970-01-06.pdf | G17: 4.32 | H17: 13.45 | I17: =G17*H17 -> 58.104 | J17: 1
B18: 3-CON-6-BA | C18: TUCANO DO SUL | D18: CAIXA 01 | E18: N/A | F18: 3CON6_PERFIL_ELETRICO_INDU€AO_1_12.250_1969-06-23.pdf | G18: 1.02 | H18: 13.45 | I18: =G18*H18 -> 13.719 | J18: 1
... B1590: SCX-2-BA | C1590: RECONCAVO | D1590: CAIXA 14 | E1590: N/A | F1590: SCX2_FIELD_PRINT_1_1000_7.875_1962-11-11.pdf | G1590: 1.58 | H1590: 13.45 | I1590: =G1590*H1590 -> 21.251 | J1590: 1

Sheet Catalogação projeto

Sheet Planilha1
A1: Data da solicitação | B1: Serviço | C1: Quantidades | D1: Endereço Petrobrás | E1: Endereço SOS Docs | F1: Cálculo final | G1: KM do trajeto | H1: KM excedente | I1: Tipo | J1: UF
A2: 45462 | B2: Implantação | C2: 50 | D2: EDIRN - Av. Euzébio Rocha, 1000, Cidade da esperança, CEP: 59070-900, NATAL RN - Bloco E sala 4 | E2: Via Urbana, 4.260, Magazine Luzia, CIA SUL, Município de Simões Filho, Bahia - CEP: 43.700-002 | G2: 1086 | H2: 1026 | I2: KM-AD | J2: BA
A3: 45463 | B3: Implantação | C3: 40 | D3: EDISER - UN - SEAL- Rua Acre n° 2.504, Bairro América, Aracaju/SE, CEP 49.080-010- Galpão S1 | E3: Via Urbana, 4.260, Magazine Luzia, CIA SUL, Município de Simões Filho, Bahia - CEP: 43.700-002 | G3: 305 | H3: 245 | I3: KM-AD | J3: SE

Sheet Planilha2
A1: Data da solicitação | B1: Serviço | C1: Quantidades | D1: Endereço Petrobrás | E1: Endereço SOS Docs | F1: Cálculo final | G1: KM do trajeto | H1: KM excedente | I1: Tipo | J1: UF
A2: 45432 | B2: Implantação | C2: 24 | D2: EDIMAN 1 - Av. Darcy Vargas, n°645, Parque Dez de Novembro, CEP: 69055-035, Manaus-AM - setor de Documentação Técnica | E2: Via Urbana, 4.260, Magazine Luzia, CIA SUL, Município de Simões Filho, Bahia - CEP: 43.700-000 | F2: 2.4 | I2: FRE-NRM | J2: BA
A3: 45457 | B3: Implantação | C3: 36 | D3: EDIMAN - Av. Darcy Vargas, 645 - Parque Dez de Novembro, Manaus - AM, 69055-035, UN-AM, 2° andar, CPGP | E3: Via Urbana, 4.260, Magazine Luzia, CIA SUL, Município de Simões Filho, Bahia - CEP: 43.700-002 | F3: 3.6 | I3: FRE-NRM | J3: BA
A4: 45433 | B4: Implantação | C4: 36 | D4: C.T. SSEBPASSÉ - BR 110 - km 378, São Sebastião do Passé, BA, 43850-000, Base Taquipe, prédio A21, Sala Documentação Técnica | E4: Via Urbana, 4.260, Magazine Luzia, CIA SUL, Município de Simões Filho, Bahia - CEP: 43.700-000 | F4: 3.6 | I4: FRE-NRM | J4: BA
A5: 45435 | B5: Implantação | C5: 15 | D5: EDISER - UN - SEAL- Rua Acre n° 2.504, Bairro América, Aracaju/SE, CEP 49.080-010- Galpão S1 | E5: Via Urbana, 4.260, Magazine Luzia, CIA SUL, Município de Simões Filho, Bahia - CEP: 43.700-000 | F5: 1.5 | I5: FRE-NRM | J5: SE
A6: 45462 | B6: Implantação | C6: 50 | D6: EDIRN - Av. Euzébio Rocha, 1000, Cidade da esperança, CEP: 59070-900, NATAL RN - Bloco E sala 4 | E6: Via Urbana, 4.260, Magazine Luzia, CIA SUL, Município de Simões Filho, Bahia - CEP: 43.700-002 | F6: 5 | I6: FRE-NRM | J6: BA
A7: 45435 | B7: Implantação | C7: 15 | D7: EDISER - UN - SEAL- Rua Acre n° 2.504, Bairro América, Aracaju/SE, CEP 49.080-010- Galpão S1 | E7: Via Urbana, 4.260, Magazine Luzia, CIA SUL, Município de Simões Filho, Bahia - CEP: 43.700-000 | F7: 1.5 | I7: FRE-NRM | J7: SE
A8: 45463 | B8: Implantação | C8: 40 | D8: EDISER - UN - SEAL- Rua Acre n° 2.504, Bairro América, Aracaju/SE, CEP 49.080-010- Galpão S1 | E8: Via Urbana, 4.260, Magazine Luzia, CIA SUL, Município de Simões Filho, Bahia - CEP: 43.700-002 | F8: 4 | I8: FRE-NRM | J8: SE
A9: 45435 | B9: Implantação | C9: 25 | D9: EDISER - UN - SEAL- Rua Acre n° 2.504, Bairro América, Aracaju/SE, CEP 49.080-010- Galpão S1 | E9: Via Urbana, 4.260, Magazine Luzia, CIA SUL, Município de Simões Filho, Bahia - CEP: 43.700-000 | F9: 2.5 | I9: FRE-NRM | J9: SE
A10: 45463 | B10: Implantação | C10: 40 | D10: EDISER - Rua Acre nº 2.504, Bairro América, Aracaju/SE, CEP: 49.080-010 - Galpão S1 | E10: Via Urbana, 4.260, Magazine Luzia, CIA SUL, Município de Simões Filho, Bahia - CEP: 43.700-002 | F10: 4 | I10: FRE-NRM | J10: SE
A11: 45435 | B11: Implantação | C11: 10 | D11: EDISER - UN - SEAL- Rua Acre n° 2.504, Bairro América, Aracaju/SE, CEP 49.080-010- Galpão S1 | E11: Via Urbana, 4.260, Magazine Luzia, CIA SUL, Município de Simões Filho, Bahia - CEP: 43.700-000 | F11: 1 | I11: FRE-NRM | J11: SE
A12: 45463 | B12: Implantação | C12: 20 | D12: EDISER - Rua Acre nº 2.504, Bairro América, Aracaju/SE, CEP: 49.080-010 - Galpão S1. | E12: Via Urbana, 4.260, Magazine Luzia, CIA SUL, Município de Simões Filho, Bahia - CEP: 43.700-002 | F12: 2 | I12: FRE-NRM | J12: SE
A13: 45435 | B13: Implantação | C13: 20 | D13: EDISER - UN - SEAL- Rua Acre n° 2.504, Bairro América, Aracaju/SE, CEP 49.080-010- Galpão S1 | E13: Via Urbana, 4.260, Magazine Luzia, CIA SUL, Município de Simões Filho, Bahia - CEP: 43.700-000 | F13: 2 | I13: FRE-NRM | J13: SE
... A28: 45447 | B28: Emprestimo | C28: 7 | D28: EDISER Rua Acre nº 2.504, Bairro América, Aracaju/SE, CEP 49.080-010, Galpão S-1, Sala de triagem de documentos | E28: Via Urbana, 4.260, Magazine Luzia, CIA SUL, Município de Simões Filho, Bahia - CEP: 43.700-002 | F28: 1 | I28: FRE-NRM | J28: SE

Sheet Planilha3
A1: Data da solicitação | B1: Serviço | C1: Quantidades | D1: Endereço Petrobrás | E1: Endereço SOS Docs | F1: Cálculo final | G1: KM do trajeto | H1: KM excedente | I1: Tipo | J1: UF
A2: 45432 | B2: Implantação | C2: 24 | D2: EDIMAN 1 - Av. Darcy Vargas, n°645, Parque Dez de Novembro, CEP: 69055-035, Manaus-AM - setor de Documentação Técnica | E2: Via Urbana, 4.260, Magazine Luzia, CIA SUL, Município de Simões Filho, Bahia - CEP: 43.700-000 | F2: 2.4 | I2: FRE-NRM | J2: BA
A3: 45433 | B3: Implantação | C3: 36 | D3: C.T. SSEBPASSÉ - BR 110 - km 378, São Sebastião do Passé, BA, 43850-000, Base Taquipe, prédio A21, Sala Documentação Técnica | E3: Via Urbana, 4.260, Magazine Luzia, CIA SUL, Município de Simões Filho, Bahia - CEP: 43.700-000 | F3: 3.6 | I3: FRE-NRM | J3: BA
A4: 45435 | B4: Implantação | C4: 15 | D4: EDISER - UN - SEAL- Rua Acre n° 2.504, Bairro América, Aracaju/SE, CEP 49.080-010- Galpão S1 | E4: Via Urbana, 4.260, Magazine Luzia, CIA SUL, Município de Simões Filho, Bahia - CEP: 43.700-000 | F4: 1.5 | I4: FRE-NRM | J4: SE
A5: 45435 | B5: Implantação | C5: 15 | D5: EDISER - UN - SEAL- Rua Acre n° 2.504, Bairro América, Aracaju/SE, CEP 49.080-010- Galpão S1 | E5: Via Urbana, 4.260, Magazine Luzia, CIA SUL, Município de Simões Filho, Bahia - CEP: 43.700-000 | F5: 1.5 | I5: FRE-NRM | J5: SE
A6: 45435 | B6: Implantação | C6: 25 | D6: EDISER - UN - SEAL- Rua Acre n° 2.504, Bairro América, Aracaju/SE, CEP 49.080-010- Galpão S1 | E6: Via Urbana, 4.260, Magazine Luzia, CIA SUL, Município de Simões Filho, Bahia - CEP: 43.700-000 | F6: 2.5 | I6: FRE-NRM | J6: SE
A7: 45435 | B7: Implantação | C7: 10 | D7: EDISER - UN - SEAL- Rua Acre n° 2.504, Bairro América, Aracaju/SE, CEP 49.080-010- Galpão S1 | E7: Via Urbana, 4.260, Magazine Luzia, CIA SUL, Município de Simões Filho, Bahia - CEP: 43.700-000 | F7: 1 | I7: FRE-NRM | J7: SE
A8: 45435 | B8: Implantação | C8: 20 | D8: EDISER - UN - SEAL- Rua Acre n° 2.504, Bairro América, Aracaju/SE, CEP 49.080-010- Galpão S1 | E8: Via Urbana, 4.260, Magazine Luzia, CIA SUL, Município de Simões Filho, Bahia - CEP: 43.700-000 | F8: 2 | I8: FRE-NRM | J8: SE
A9: 45435 | B9: Implantação | C9: 24 | D9: EDISER - UN - SEAL- Rua Acre n° 2.504, Bairro América, Aracaju/SE, CEP 49.080-010- Galpão S1 | E9: Via Urbana, 4.260, Magazine Luzia, CIA SUL, Município de Simões Filho, Bahia - CEP: 43.700-000 | F9: 2.4 | I9: FRE-NRM | J9: SE
A10: 45435 | B10: Implantação | C10: 15 | D10: EDISER - UN - SEAL- Rua Acre n° 2.504, Bairro América, Aracaju/SE, CEP 49.080-010- Galpão S1 | E10: Via Urbana, 4.260, Magazine Luzia, CIA SUL, Município de Simões Filho, Bahia - CEP: 43.700-000 | F10: 1.5 | I10: FRE-NRM | J10: SE
A11: 45435 | B11: Implantação | C11: 15 | D11: EDISER - UN - SEAL- Rua Acre n° 2.504, Bairro América, Aracaju/SE, CEP 49.080-010- Galpão S1 | E11: Via Urbana, 4.260, Magazine Luzia, CIA SUL, Município de Simões Filho, Bahia - CEP: 43.700-000 | F11: 1.5 | I11: FRE-NRM | J11: SE
A12: 45446 | B12: Implantação | C12: 33 | D12: EDIRN - Av. Euzébio Rocha, 1000, Cidade da esperança, CEP: 59070-900, NATAL RN - Bloco E sala 4 | E12: Via Urbana, 4.260, Magazine Luzia, CIA SUL, Município de Simões Filho, Bahia - CEP: 43.700-001 | F12: 3.3 | I12: FRE-NRM | J12: BA
A13: 45446 | B13: Implantação | C13: 50 | D13: EDIRN - Av. Euzébio Rocha, 1000, Cidade da esperança, CEP: 59070-900, NATAL RN - Bloco E sala 4 | E13: Via Urbana, 4.260, Magazine Luzia, CIA SUL, Município de Simões Filho, Bahia - CEP: 43.700-002 | F13: 5 | I13: FRE-NRM | J13: BA
... A28: 45457 | B28: Implantação | C28: 36 | D28: EDIMAN - Av. Darcy Vargas, 645 - Parque Dez de Novembro, Manaus - AM, 69055-035, UN-AM, 2° andar, CPGP | E28: Via Urbana, 4.260, Magazine Luzia, CIA SUL, Município de Simões Filho, Bahia - CEP: 43.700-002 | F28: 3.6 | I28: FRE-NRM | J28: BA
A29: 45463 | B29: Implantação | C29: 40 | D29: EDISER - UN - SEAL- Rua Acre n° 2.504, Bairro América, Aracaju/SE, CEP 49.080-010- Galpão S1 | E29: Via Urbana, 4.260, Magazine Luzia, CIA SUL, Município de Simões Filho, Bahia - CEP: 43.700-002 | G29: 305 | H29: 245 | I29: KM-AD | J29: SE
A30: 45462 | B30: Implantação | C30: 50 | D30: EDIRN - Av. Euzébio Rocha, 1000, Cidade da esperança, CEP: 59070-900, NATAL RN - Bloco E sala 4 | E30: Via Urbana, 4.260, Magazine Luzia, CIA SUL, Município de Simões Filho, Bahia - CEP: 43.700-002 | G30: 1086 | H30: 1026 | I30: KM-AD | J30: BA
A31: 45432 | B31: Implantação | C31: 24 | D31: EDIMAN 1 - Av. Darcy Vargas, n°645, Parque Dez de Novembro, CEP: 69055-035, Manaus-AM - setor de Documentação Técnica | E31: Via Urbana, 4.260, Magazine Luzia, CIA SUL, Município de Simões Filho, Bahia - CEP: 43.700-000 | G31: 4851 | H31: 4791 | I31: KM-AD: | J31: BA
A32: 45435 | B32: Implantação | C32: 15 | D32: EDISER - UN - SEAL- Rua Acre n° 2.504, Bairro América, Aracaju/SE, CEP 49.080-010- Galpão S1 | E32: Via Urbana, 4.260, Magazine Luzia, CIA SUL, Município de Simões Filho, Bahia - CEP: 43.700-000 | G32: 305 | H32: 245 | I32: KM-AD: | J32: SE
A33: 45435 | B33: Implantação | C33: 15 | D33: EDISER - UN - SEAL- Rua Acre n° 2.504, Bairro América, Aracaju/SE, CEP 49.080-010- Galpão S1 | E33: Via Urbana, 4.260, Magazine Luzia, CIA SUL, Município de Simões Filho, Bahia - CEP: 43.700-000 | G33: 305 | H33: 245 | I33: KM-AD: | J33: SE
A34: 45435 | B34: Implantação | C34: 25 | D34: EDISER - UN - SEAL- Rua Acre n° 2.504, Bairro América, Aracaju/SE, CEP 49.080-010- Galpão S1 | E34: Via Urbana, 4.260, Magazine Luzia, CIA SUL, Município de Simões Filho, Bahia - CEP: 43.700-000 | G34: 305 | H34: 245 | I34: KM-AD: | J34: SE
A35: 45435 | B35: Implantação | C35: 10 | D35: EDISER - UN - SEAL- Rua Acre n° 2.504, Bairro América, Aracaju/SE, CEP 49.080-010- Galpão S1 | E35: Via Urbana, 4.260, Magazine Luzia, CIA SUL, Município de Simões Filho, Bahia - CEP: 43.700-000 | G35: 305 | H35: 245 | I35: KM-AD: | J35: SE
A36: 45435 | B36: Implantação | C36: 20 | D36: EDISER - UN - SEAL- Rua Acre n° 2.504, Bairro América, Aracaju/SE, CEP 49.080-010- Galpão S1 | E36: Via Urbana, 4.260, Magazine Luzia, CIA SUL, Município de Simões Filho, Bahia - CEP: 43.700-000 | G36: 305 | H36: 245 | I36: KM-AD: | J36: SE
A37: 45435 | B37: Implantação | C37: 24 | D37: EDISER - UN - SEAL- Rua Acre n° 2.504, Bairro América, Aracaju/SE, CEP 49.080-010- Galpão S1 | E37: Via Urbana, 4.260, Magazine Luzia, CIA SUL, Município de Simões Filho, Bahia - CEP: 43.700-000 | G37: 305 | H37: 245 | I37: KM-AD: | J37: SE
A38: 45435 | B38: Implantação | C38: 15 | D38: EDISER - UN - SEAL- Rua Acre n° 2.504, Bairro América, Aracaju/SE, CEP 49.080-010- Galpão S1 | E38: Via Urbana, 4.260, Magazine Luzia, CIA SUL, Município de Simões Filho, Bahia - CEP: 43.700-000 | G38: 305 | H38: 245 | I38: KM-AD: | J38: SE
A39: 45435 | B39: Implantação | C39: 15 | D39: EDISER - UN - SEAL- Rua Acre n° 2.504, Bairro América, Aracaju/SE, CEP 49.080-010- Galpão S1 | E39: Via Urbana, 4.260, Magazine Luzia, CIA SUL, Município de Simões Filho, Bahia - CEP: 43.700-000 | G39: 305 | H39: 245 | I39: KM-AD: | J39: SE
A40: 45446 | B40: Implantação | C40: 33 | D40: EDIRN - Av. Euzébio Rocha, 1000, Cidade da esperança, CEP: 59070-900, NATAL RN - Bloco E sala 4 | E40: Via Urbana, 4.260, Magazine Luzia, CIA SUL, Município de Simões Filho, Bahia - CEP: 43.700-001 | G40: 1086 | H40: 1026 | I40: KM-AD: | J40: BA
... A51: 45463 | B51: Implantação | C51: 40 | D51: EDISER - Rua Acre nº 2.504, Bairro América, Aracaju/SE, CEP: 49.080-010 - Galpão S1 | E51: Via Urbana, 4.260, Magazine Luzia, CIA SUL, Município de Simões Filho, Bahia - CEP: 43.700-002 | G51: 305 | H51: 245 | I51: KM-AD: | J51: SE

Sheet Fretes cálculo
A1: Data da solicitação | B1: Serviço | C1: Quantidades | D1: Endereço Petrobrás | E1: Endereço PA Arquivos | F1: Cálculo final | G1: KM do trajeto | H1: KM excedente | I1: Tipo | J1: UF
A2: 46211 | B2: Implantação | C2: 5 | D2: RNEST | E2: CLPA-Camaçari | F2: 1 | G2: 746 | H2: =Table_5[[#This Row],[KM do trajeto]]-100 -> 646 | I2: KM-AD | J2: PE
A3: 46211 | B3: Implantação | C3: 11 | D3: RNEST | E3: CLPA-Camaçari | F3: 1 | G3: 746 | H3: =Table_5[[#This Row],[KM do trajeto]]-100 -> 646 | I3: KM-AD | J3: PE
A4: 46226 | B4: Implantação | C4: 22 | D4: EDIRN | E4: CLPA-Camaçari | F4: 1 | G4: 1058 | H4: =Table_5[[#This Row],[KM do trajeto]]-100 -> 958 | I4: KM-AD | J4: RN
A5: 24/072026 | B5: Implantação | C5: 9 | D5: EDIRN | E5: CLPA-Camaçari | F5: 1 | G5: 1058 | H5: =Table_5[[#This Row],[KM do trajeto]]-100 -> 958 | I5: KM-AD | J5: RN
A6: 24/072026 | B6: Implantação | C6: 1 | D6: UTE-BAHIA | E6: CLPA-Camaçari | F6: 1 | G6: 46 | H6: =Table_5[[#This Row],[KM do trajeto]]-100 -> -54 | I6: FRE-NRM | J6: BA
A7: 23/07/2026 | B7: Materiais | C7: 80 | D7: C.T. SSEBPASSÉ | E7: CLPA-Camaçari | F7: 1 | G7: 44 | H7: =Table_5[[#This Row],[KM do trajeto]]-100 -> -56 | I7: FRE-NRM | J7: BA

Sheet Relação de ordens de serviço
B3: OS | C3: Click | D3: Status
B4: 10000 | C4: 52 | D4: No Prazo
B5: 2000 | C5: 45 | D5: Forado prazo
B6: 500 | C6: 10 | D6: No Prazo

Sheet Combos
B2: LINHA DE NEGÓCIO | C2: UNIDADE | D2: SERVIÇO | E2: TIPO | F2: ENDEREÇO SOS DOCS | G2: ENDEREÇO PETROBRAS | H2: DOCUMENTO | I2: FC | J2: Parcionamento | K2: Tipo de Prazo
B3: Implantação | C3: RJ | D3: FRE-NRM | E3: Dossiê | F3: Via Urbana, 4.260, Magazine Luzia, CIA SUL, Município de Simões Filho, Bahia - CEP: 43.700-000 | G3: ESTAÇÃO VANDEMIR FERREIRA - Rod BA 523 S/N FAZ. USINA SAO PAULO CAMPO DE CANDEIAS - SÃO FRANCISCO DO CONDE - BA | H3: Microfilme | I3: 1 | J3: SIM | K3: Normal
B4: Devolução | C4: SP | D4: FRE-EXP | E4: Processo | G4: FAFEN-BA ATUALPROCGEL - R. Eteno, 2198 - Polo Petroquímico, Camaçari - BA, 42810-000 (Prédio ADM 1) | H4: Microficha | I4: 1 | J4: NÃO | K4: Expresso
B5: Empréstimo | C5: DF | E5: Doc. Avulso | G5: ESTRADA ENGENHO SOLEDADE, BR 101, S/N , Zona Rural, Japaratuba, SE CEP: 49960-000.- BASE CARMOPOLIS - SALA DO TRANSPORTE | H5: Documento - Formato A4 | I5: 1 | K5: Agendada
B6: Saida Definitiva | C6: ES | E6: Nota Fiscal | G6: Av. Darcy Vargas, 645 - Parque Dez de Novembro, Manaus - AM, 69055-035, UN-AM, 3° andar, CPGP | H6: Documento - Formato A3 | I6: 2
B7: Suprimentos | E7: Contrato | G7: Refinaria de Mataripe.-Rodovia BA- 523- K4- Mataripe- São Francisco do Conde/BA - CEP: 3970-970 | H7: Documento - Formato A2 | I7: 4
B8: Digitalização | E8: Documentação contratual | G8: Av. Leite Barbosa, S/N - Mucuripe - Fortaleza – Ceará CEP: 60180-420, UO-LUBNOR - Engenharia, 2º Andar | H8: Documento - Formato A1 | I8: 8
B9: Cópia | E9: Documentação técnica | G9: Base Taquipe - BR 110, KM 378 - SÃO SEBASTIÃO DO PASSÉ - Documentação Técnica, prédio A-21 | H9: Documento - Formato A0 | I9: 16
E10: Documentação bibliográfica | G10: EDISER - Rua Acre, 2.504 , Galpão S5 - Bairro AMERICA, Aracaju, SE - CEP: 49080-010 | H10: Documento - Superior ao Formato A0 | I10: 13.45
E11: Documentação contábil e financeira | G11: RNEST: Rodovia PE-60, Km 10 S/N, Complexo Portuário de Suape, Refinaria Abreu e Lima - Ipojuca/PE CEP 55590-000. Prédio do Administrativo, Bloco A – Biblioteca | H11: Mídia DVD
E12: Documentação administrativa | G12: Usina de Biodiesel de Candeias: Rod. BA 522, KM 11 s/n Jabequara das Flores - Candeias/BA, Acesso no trevo do petróleo.
G13: EDIMAN - Av. Darcy Vargas, 645 - Parque Dez de Novembro, Manaus - AM, 69055-035, UN-AM, 2° andar, SALA 201 - (DOCUMENTAÇÃO TÉCNICA )
G14: Aeroporto Santa Maria - Av. Senador Júlio César Leite, SN, Bairro: Aeroporto - CEP 49037-580 - Aracaju - SE. Sala da Petrobras na área restrita do aeroporto.
G15: Refinaria Clara Camarão - ATI Guamaré - Rod. RN 221, S/N - Guamaré-RN - recepção do ativo industrial
G16: Polo Industrial de Guamaré - Rod. RN221 - KM 25, GUAMARÉ/RN
G17: UN-RNCE (Prédio EDIRN) - AV. EUZÉBIO ROCHA, 1000, CIDADE DA ESPERANÇA, NATAL-RN, CEP: 59070-900
G18: ESTAÇÃO PILAR - FAZENDA LAMARÃO S/N, ACESSO BR316, KM 266, ZONA RURAL - PILAR-AL - CEP 57150-000, Prédio da TIC
G19: Av. Melício Machado, sn, km2, bairro Atalaia, Aracaju – SE -
G20: Rodovia BA 516- campo Buracica- Alagoinhas-BA -CEP- 48000-000- BASE ADMINSTRATIVA DE BURACICA
G21: AV WILSON ROSADO DE SA, S/N , ALTO SUMARÉ, Mossoró, RN CEP: 59633-900
G22: BR-304, Estrada do contorno, KM-46. - Base Petrobras Mossoró - Oficina do IP
G23: C.T. ARAÇÁS - RODOVIA BA 093 KM 108, ARAÇÁS, BAHIA
G24: C.T. CANDEIAS -Rodovia BA- 523- K4- Mataripe- São Francisco do Conde/BA - CEP: 43900-000, UPGN – CANDEIAS- CRE DE CANDEIAS
... G35: FAZENDA: ALTO ALEGRE, POÇO 1 ARG.1 ALTO DO RODRIGUES/RN

Sheet Base
B2: Status Primário | D2: Status Secundário | F2: Solicitante | H2: Coordenador | J2: Status do prazo | L2: Medição | N2: Estados | P2: Tipo de Solicitação
D3: Ordens atendidas no prazo | F3: Gustavo Henrique Ferreira | H3: Adson Santos | J3: No Prazo | L3: 23/12/2023 a 25/01/2024 | N3: BA | P3: Normal
B4: Ordens em atendimento | D4: Ordens atendidas fora do prazo | F4: Carolina Santos de mendonça | J4: Fora do Prazo | L4: 26/01/2024 a 25/02/2024 | N4: PE | P4: Urgente
B5: Ordens pendentes | D5: Ordens pendentes no prazo | F5: Viviane Rosa Rangel | L5: 24/02/2024 a 25/03/2024 | N5: CE | P5: Agendado
B6: Ordens atendidas | D6: Ordens pendentes fora do prazo | F6: Serviço de guarda | L6: 26/03/2024 a 25/04/2024 | N6: AM
F7: JACKELINE SOUZA FREITAS | L7: 26/04/2024 a 25/05/2024 | N7: RN
F8: TATIANA SOUZA FREITAS | L8: 26/05/2024 a 25/06/2024 | N8: SE
L9: 26/06/2024 a 25/07/2024 | N9: AL
L10: 26/07/2024 a 25/08/2024
B11: Status da OS | L11: 26/08/2024 a 25/09/2024
B12: Aguardando atendimento | L12: 26/09/2024 a 25/10/2024
B13: Em atendimento | L13: 26/10/2024 a 25/11/2024
B14: Atendida | L14: 26/11/2024 a 25/12/2024
